{
	"item name" : "Book",
	"transactions" : 
	[
		{
			"amount" : 1,
			"buyer" : "NullCase",
			"location" : 
			{
				"x" : 60,
				"y" : 71,
				"z" : -17
			},
			"seller" : "K9us",
			"time" : "2018/09/20",
			"type" : "buy",
			"volume" : 250,
			"world" : "world"
		},
		{
			"amount" : 3,
			"buyer" : "3thanat0r",
			"location" : 
			{
				"x" : 269,
				"y" : 3,
				"z" : -5
			},
			"seller" : "Cardano_ff",
			"time" : "2018/09/25",
			"type" : "buy",
			"volume" : 3000,
			"world" : "world_the_end"
		},
		{
			"amount" : 4,
			"buyer" : "spfoia",
			"location" : 
			{
				"x" : 60,
				"y" : 71,
				"z" : -17
			},
			"seller" : "K9us",
			"time" : "2018/09/28",
			"type" : "buy",
			"volume" : 1000,
			"world" : "world"
		},
		{
			"amount" : 43,
			"buyer" : "NullCase",
			"location" : 
			{
				"x" : 60,
				"y" : 71,
				"z" : -17
			},
			"seller" : "K9us",
			"time" : "2018/09/30",
			"type" : "buy",
			"volume" : 10750,
			"world" : "world"
		},
		{
			"amount" : 3,
			"buyer" : "Jesper1972",
			"location" : 
			{
				"x" : 60,
				"y" : 71,
				"z" : -17
			},
			"seller" : "K9us",
			"time" : "2018/10/01",
			"type" : "buy",
			"volume" : 750,
			"world" : "world"
		},
		{
			"amount" : 1,
			"buyer" : "Vrael1",
			"location" : 
			{
				"x" : 269,
				"y" : 3,
				"z" : -5
			},
			"seller" : "Cardano_ff",
			"time" : "2018/10/02",
			"type" : "buy",
			"volume" : 1000,
			"world" : "world_the_end"
		},
		{
			"amount" : 1,
			"buyer" : "TheScrubJay",
			"location" : 
			{
				"x" : 269,
				"y" : 3,
				"z" : -5
			},
			"seller" : "Cardano_ff",
			"time" : "2018/10/04",
			"type" : "buy",
			"volume" : 1000,
			"world" : "world_the_end"
		},
		{
			"amount" : 35,
			"buyer" : "frozenhammerz",
			"location" : 
			{
				"x" : 60,
				"y" : 71,
				"z" : -17
			},
			"seller" : "K9us",
			"time" : "2018/10/04",
			"type" : "buy",
			"volume" : 8750,
			"world" : "world"
		},
		{
			"amount" : 21,
			"buyer" : "Butokuden",
			"location" : 
			{
				"x" : 60,
				"y" : 71,
				"z" : -17
			},
			"seller" : "K9us",
			"time" : "2018/10/07",
			"type" : "buy",
			"volume" : 3150,
			"world" : "world"
		},
		{
			"amount" : 6,
			"buyer" : "Butokuden",
			"location" : 
			{
				"x" : -346,
				"y" : 70,
				"z" : 79
			},
			"seller" : "AteUrC00ki35",
			"time" : "2018/10/07",
			"type" : "buy",
			"volume" : 900,
			"world" : "world"
		},
		{
			"amount" : 33,
			"buyer" : "Daedalus_Dingus",
			"location" : 
			{
				"x" : 60,
				"y" : 71,
				"z" : -17
			},
			"seller" : "K9us",
			"time" : "2018/10/10",
			"type" : "buy",
			"volume" : 4950,
			"world" : "world"
		},
		{
			"amount" : 18,
			"buyer" : "Daedalus_Dingus",
			"location" : 
			{
				"x" : 60,
				"y" : 71,
				"z" : -17
			},
			"seller" : "K9us",
			"time" : "2018/10/14",
			"type" : "buy",
			"volume" : 2700,
			"world" : "world"
		},
		{
			"amount" : 15,
			"buyer" : "Mr_Digs",
			"location" : 
			{
				"x" : -346,
				"y" : 70,
				"z" : 79
			},
			"seller" : "AteUrC00ki35",
			"time" : "2018/10/19",
			"type" : "buy",
			"volume" : 2250,
			"world" : "world"
		},
		{
			"amount" : 2,
			"buyer" : "Butokuden",
			"location" : 
			{
				"x" : 269,
				"y" : 3,
				"z" : -5
			},
			"seller" : "Cardano_ff",
			"time" : "2018/10/22",
			"type" : "buy",
			"volume" : 2000,
			"world" : "world_the_end"
		},
		{
			"amount" : 1,
			"buyer" : "Magnavox",
			"location" : 
			{
				"x" : 269,
				"y" : 3,
				"z" : -5
			},
			"seller" : "Cardano_ff",
			"time" : "2018/10/28",
			"type" : "buy",
			"volume" : 1000,
			"world" : "world_the_end"
		},
		{
			"amount" : 1,
			"buyer" : "Dragonslair7",
			"location" : 
			{
				"x" : 269,
				"y" : 3,
				"z" : -5
			},
			"seller" : "Cardano_ff",
			"time" : "2018/10/31",
			"type" : "buy",
			"volume" : 1000,
			"world" : "world_the_end"
		},
		{
			"amount" : 4,
			"buyer" : "K9us",
			"location" : 
			{
				"x" : 16,
				"y" : 72,
				"z" : -41
			},
			"seller" : "Captain_Handsome",
			"time" : "2018/11/03",
			"type" : "buy",
			"volume" : 200,
			"world" : "world"
		},
		{
			"amount" : 178,
			"buyer" : "Captain_Handsome",
			"location" : 
			{
				"x" : 16,
				"y" : 72,
				"z" : -41
			},
			"seller" : "K9us",
			"time" : "2018/11/03",
			"type" : "sell",
			"volume" : 8010,
			"world" : "world"
		},
		{
			"amount" : 64,
			"buyer" : "Aewheros",
			"location" : 
			{
				"x" : 60,
				"y" : 71,
				"z" : -17
			},
			"seller" : "K9us",
			"time" : "2018/11/03",
			"type" : "buy",
			"volume" : 3200,
			"world" : "world"
		},
		{
			"amount" : 188,
			"buyer" : "Captain_Handsome",
			"location" : 
			{
				"x" : 16,
				"y" : 72,
				"z" : -41
			},
			"seller" : "NullCase",
			"time" : "2018/11/04",
			"type" : "sell",
			"volume" : 8460,
			"world" : "world"
		},
		{
			"amount" : 32,
			"buyer" : "Cardano_ff",
			"location" : 
			{
				"x" : 16,
				"y" : 72,
				"z" : -41
			},
			"seller" : "Captain_Handsome",
			"time" : "2018/11/04",
			"type" : "buy",
			"volume" : 320,
			"world" : "world"
		},
		{
			"amount" : 448,
			"buyer" : "Aewheros",
			"location" : 
			{
				"x" : 16,
				"y" : 72,
				"z" : -41
			},
			"seller" : "Captain_Handsome",
			"time" : "2018/11/04",
			"type" : "buy",
			"volume" : 4480,
			"world" : "world"
		},
		{
			"amount" : 48,
			"buyer" : "Jesper1972",
			"location" : 
			{
				"x" : 16,
				"y" : 72,
				"z" : -41
			},
			"seller" : "Captain_Handsome",
			"time" : "2018/11/04",
			"type" : "buy",
			"volume" : 480,
			"world" : "world"
		},
		{
			"amount" : 64,
			"buyer" : "Aewheros",
			"location" : 
			{
				"x" : 16,
				"y" : 72,
				"z" : -41
			},
			"seller" : "Captain_Handsome",
			"time" : "2018/11/04",
			"type" : "buy",
			"volume" : 640,
			"world" : "world"
		},
		{
			"amount" : 32,
			"buyer" : "Captain_Handsome",
			"location" : 
			{
				"x" : 16,
				"y" : 72,
				"z" : -41
			},
			"seller" : "NullCase",
			"time" : "2018/11/04",
			"type" : "sell",
			"volume" : 200,
			"world" : "world"
		},
		{
			"amount" : 16,
			"buyer" : "NullCase",
			"location" : 
			{
				"x" : 16,
				"y" : 72,
				"z" : -41
			},
			"seller" : "Captain_Handsome",
			"time" : "2018/11/05",
			"type" : "buy",
			"volume" : 160,
			"world" : "world"
		},
		{
			"amount" : 15,
			"buyer" : "Captain_Handsome",
			"location" : 
			{
				"x" : 16,
				"y" : 72,
				"z" : -41
			},
			"seller" : "NullCase",
			"time" : "2018/11/05",
			"type" : "sell",
			"volume" : 93.75,
			"world" : "world"
		},
		{
			"amount" : 1,
			"buyer" : "frozenhammerz",
			"location" : 
			{
				"x" : -1951,
				"y" : 62,
				"z" : 1560
			},
			"seller" : "K9us",
			"time" : "2018/11/05",
			"type" : "buy",
			"volume" : 200,
			"world" : "world"
		},
		{
			"amount" : 1,
			"buyer" : "K9us",
			"location" : 
			{
				"x" : -1951,
				"y" : 62,
				"z" : 1560
			},
			"seller" : "frozenhammerz",
			"time" : "2018/11/05",
			"type" : "sell",
			"volume" : 100,
			"world" : "world"
		},
		{
			"amount" : 184,
			"buyer" : "Aewheros",
			"location" : 
			{
				"x" : 16,
				"y" : 72,
				"z" : -41
			},
			"seller" : "Captain_Handsome",
			"time" : "2018/11/10",
			"type" : "buy",
			"volume" : 1840,
			"world" : "world"
		},
		{
			"amount" : 1,
			"buyer" : "Stormrunners",
			"location" : 
			{
				"x" : 37,
				"y" : 63,
				"z" : -19
			},
			"seller" : "K9us",
			"time" : "2018/11/23",
			"type" : "buy",
			"volume" : 30,
			"world" : "world"
		},
		{
			"amount" : 2,
			"buyer" : "rubez",
			"location" : 
			{
				"x" : 37,
				"y" : 63,
				"z" : -19
			},
			"seller" : "K9us",
			"time" : "2018/11/25",
			"type" : "buy",
			"volume" : 60,
			"world" : "world"
		},
		{
			"amount" : 6,
			"buyer" : "MiChupacabaras",
			"location" : 
			{
				"x" : -346,
				"y" : 70,
				"z" : 78
			},
			"seller" : "AteUrC00ki35",
			"time" : "2018/11/26",
			"type" : "buy",
			"volume" : 3000,
			"world" : "world"
		},
		{
			"amount" : 59,
			"buyer" : "Phantom_Ark",
			"location" : 
			{
				"x" : 60,
				"y" : 71,
				"z" : -17
			},
			"seller" : "K9us",
			"time" : "2018/11/29",
			"type" : "buy",
			"volume" : 5900,
			"world" : "world"
		},
		{
			"amount" : 133,
			"buyer" : "DIOSWILSON",
			"location" : 
			{
				"x" : 37,
				"y" : 63,
				"z" : -19
			},
			"seller" : "K9us",
			"time" : "2018/12/04",
			"type" : "buy",
			"volume" : 3990,
			"world" : "world"
		},
		{
			"amount" : 5,
			"buyer" : "freakdown",
			"location" : 
			{
				"x" : -346,
				"y" : 70,
				"z" : 78
			},
			"seller" : "AteUrC00ki35",
			"time" : "2018/12/07",
			"type" : "buy",
			"volume" : 2500,
			"world" : "world"
		},
		{
			"amount" : 2,
			"buyer" : "DIOSWILSON",
			"location" : 
			{
				"x" : 37,
				"y" : 63,
				"z" : -19
			},
			"seller" : "K9us",
			"time" : "2018/12/10",
			"type" : "buy",
			"volume" : 60,
			"world" : "world"
		},
		{
			"amount" : 3,
			"buyer" : "cmanley1981",
			"location" : 
			{
				"x" : 269,
				"y" : 3,
				"z" : -5
			},
			"seller" : "Cardano_ff",
			"time" : "2018/12/10",
			"type" : "buy",
			"volume" : 3000,
			"world" : "world_the_end"
		},
		{
			"amount" : 1,
			"buyer" : "DIOSWILSON",
			"location" : 
			{
				"x" : 37,
				"y" : 63,
				"z" : -19
			},
			"seller" : "K9us",
			"time" : "2018/12/12",
			"type" : "buy",
			"volume" : 30,
			"world" : "world"
		},
		{
			"amount" : 1,
			"buyer" : "DIOSWILSON",
			"location" : 
			{
				"x" : 37,
				"y" : 63,
				"z" : -19
			},
			"seller" : "K9us",
			"time" : "2018/12/13",
			"type" : "buy",
			"volume" : 30,
			"world" : "world"
		},
		{
			"amount" : 1,
			"buyer" : "NullCase",
			"location" : 
			{
				"x" : -63,
				"y" : 63,
				"z" : 10
			},
			"seller" : "K9us",
			"time" : "2018/12/20",
			"type" : "sell",
			"volume" : 24,
			"world" : "world"
		},
		{
			"amount" : 11,
			"buyer" : "K9us",
			"location" : 
			{
				"x" : -63,
				"y" : 63,
				"z" : 10
			},
			"seller" : "NullCase",
			"time" : "2018/12/20",
			"type" : "buy",
			"volume" : 308,
			"world" : "world"
		},
		{
			"amount" : 64,
			"buyer" : "G4t1t4M1m0s4",
			"location" : 
			{
				"x" : 37,
				"y" : 63,
				"z" : -19
			},
			"seller" : "K9us",
			"time" : "2018/12/24",
			"type" : "buy",
			"volume" : 1920,
			"world" : "world"
		},
		{
			"amount" : 234,
			"buyer" : "NullCase",
			"location" : 
			{
				"x" : -63,
				"y" : 63,
				"z" : 10
			},
			"seller" : "K9us",
			"time" : "2018/12/29",
			"type" : "sell",
			"volume" : 25740,
			"world" : "world"
		},
		{
			"amount" : 1,
			"buyer" : "K9us",
			"location" : 
			{
				"x" : -346,
				"y" : 70,
				"z" : 78
			},
			"seller" : "AteUrC00ki35",
			"time" : "2019/01/01",
			"type" : "buy",
			"volume" : 500,
			"world" : "world"
		},
		{
			"amount" : 1,
			"buyer" : "magemagemege",
			"location" : 
			{
				"x" : 60,
				"y" : 71,
				"z" : -17
			},
			"seller" : "K9us",
			"time" : "2019/01/01",
			"type" : "buy",
			"volume" : 120,
			"world" : "world"
		},
		{
			"amount" : 2,
			"buyer" : "magemagemege",
			"location" : 
			{
				"x" : 37,
				"y" : 63,
				"z" : -19
			},
			"seller" : "K9us",
			"time" : "2019/01/01",
			"type" : "buy",
			"volume" : 240,
			"world" : "world"
		},
		{
			"amount" : 2,
			"buyer" : "magemagemege",
			"location" : 
			{
				"x" : 60,
				"y" : 71,
				"z" : -17
			},
			"seller" : "K9us",
			"time" : "2019/01/01",
			"type" : "buy",
			"volume" : 240,
			"world" : "world"
		},
		{
			"amount" : 1,
			"buyer" : "magemagemege",
			"location" : 
			{
				"x" : 37,
				"y" : 63,
				"z" : -19
			},
			"seller" : "K9us",
			"time" : "2019/01/01",
			"type" : "buy",
			"volume" : 120,
			"world" : "world"
		},
		{
			"amount" : 1,
			"buyer" : "Downhilldriver",
			"location" : 
			{
				"x" : 37,
				"y" : 63,
				"z" : -19
			},
			"seller" : "K9us",
			"time" : "2019/01/02",
			"type" : "buy",
			"volume" : 120,
			"world" : "world"
		},
		{
			"amount" : 123,
			"buyer" : "K9us",
			"location" : 
			{
				"x" : 37,
				"y" : 63,
				"z" : -19
			},
			"seller" : "magemagemege",
			"time" : "2019/01/02",
			"type" : "sell",
			"volume" : 14145,
			"world" : "world"
		},
		{
			"amount" : 256,
			"buyer" : "K9us",
			"location" : 
			{
				"x" : 60,
				"y" : 71,
				"z" : -17
			},
			"seller" : "magemagemege",
			"time" : "2019/01/02",
			"type" : "sell",
			"volume" : 29440,
			"world" : "world"
		},
		{
			"amount" : 259,
			"buyer" : "K9us",
			"location" : 
			{
				"x" : 37,
				"y" : 63,
				"z" : -19
			},
			"seller" : "magemagemege",
			"time" : "2019/01/03",
			"type" : "sell",
			"volume" : 29785,
			"world" : "world"
		},
		{
			"amount" : 1,
			"buyer" : "Stormrunners",
			"location" : 
			{
				"x" : -63,
				"y" : 63,
				"z" : 10
			},
			"seller" : "NullCase",
			"time" : "2019/01/03",
			"type" : "buy",
			"volume" : 120,
			"world" : "world"
		},
		{
			"amount" : 79,
			"buyer" : "K9us",
			"location" : 
			{
				"x" : 37,
				"y" : 63,
				"z" : -19
			},
			"seller" : "NorraLigan",
			"time" : "2019/01/07",
			"type" : "sell",
			"volume" : 9085,
			"world" : "world"
		},
		{
			"amount" : 64,
			"buyer" : "NorraLigan",
			"location" : 
			{
				"x" : 37,
				"y" : 63,
				"z" : -19
			},
			"seller" : "K9us",
			"time" : "2019/01/07",
			"type" : "buy",
			"volume" : 7680,
			"world" : "world"
		},
		{
			"amount" : 124,
			"buyer" : "K9us",
			"location" : 
			{
				"x" : 37,
				"y" : 63,
				"z" : -19
			},
			"seller" : "NorraLigan",
			"time" : "2019/01/07",
			"type" : "sell",
			"volume" : 14260,
			"world" : "world"
		},
		{
			"amount" : 3,
			"buyer" : "NorraLigan",
			"location" : 
			{
				"x" : -2757,
				"y" : 20,
				"z" : 1815
			},
			"seller" : "K9us",
			"time" : "2019/01/07",
			"type" : "buy",
			"volume" : 180,
			"world" : "world"
		},
		{
			"amount" : 3,
			"buyer" : "NorraLigan",
			"location" : 
			{
				"x" : -2498,
				"y" : 11,
				"z" : 1253
			},
			"seller" : "K9us",
			"time" : "2019/01/07",
			"type" : "buy",
			"volume" : 45,
			"world" : "world"
		},
		{
			"amount" : 5,
			"buyer" : "Stormrunners",
			"location" : 
			{
				"x" : 37,
				"y" : 63,
				"z" : -19
			},
			"seller" : "K9us",
			"time" : "2019/01/07",
			"type" : "buy",
			"volume" : 600,
			"world" : "world"
		},
		{
			"amount" : 1,
			"buyer" : "NorraLigan",
			"location" : 
			{
				"x" : -63,
				"y" : 63,
				"z" : 10
			},
			"seller" : "NullCase",
			"time" : "2019/01/26",
			"type" : "buy",
			"volume" : 120,
			"world" : "world"
		},
		{
			"amount" : 10,
			"buyer" : "Aewheros",
			"location" : 
			{
				"x" : -63,
				"y" : 63,
				"z" : 10
			},
			"seller" : "NullCase",
			"time" : "2019/01/29",
			"type" : "buy",
			"volume" : 1200,
			"world" : "world"
		},
		{
			"amount" : 64,
			"buyer" : "Magranon",
			"location" : 
			{
				"x" : 60,
				"y" : 71,
				"z" : -17
			},
			"seller" : "K9us",
			"time" : "2019/01/30",
			"type" : "buy",
			"volume" : 7680,
			"world" : "world"
		},
		{
			"amount" : 1,
			"buyer" : "nilssssss",
			"location" : 
			{
				"x" : 60,
				"y" : 71,
				"z" : -17
			},
			"seller" : "K9us",
			"time" : "2019/01/30",
			"type" : "buy",
			"volume" : 120,
			"world" : "world"
		},
		{
			"amount" : 1,
			"buyer" : "K9us",
			"location" : 
			{
				"x" : 60,
				"y" : 71,
				"z" : -17
			},
			"seller" : "nilssssss",
			"time" : "2019/01/30",
			"type" : "sell",
			"volume" : 115,
			"world" : "world"
		},
		{
			"amount" : 1,
			"buyer" : "nilssssss",
			"location" : 
			{
				"x" : 37,
				"y" : 63,
				"z" : -19
			},
			"seller" : "K9us",
			"time" : "2019/02/02",
			"type" : "buy",
			"volume" : 120,
			"world" : "world"
		},
		{
			"amount" : 1,
			"buyer" : "nilssssss",
			"location" : 
			{
				"x" : -63,
				"y" : 63,
				"z" : 10
			},
			"seller" : "NullCase",
			"time" : "2019/02/02",
			"type" : "buy",
			"volume" : 120,
			"world" : "world"
		},
		{
			"amount" : 28,
			"buyer" : "nilssssss",
			"location" : 
			{
				"x" : 37,
				"y" : 63,
				"z" : -19
			},
			"seller" : "K9us",
			"time" : "2019/02/02",
			"type" : "buy",
			"volume" : 3360,
			"world" : "world"
		},
		{
			"amount" : 64,
			"buyer" : "nilssssss",
			"location" : 
			{
				"x" : 37,
				"y" : 63,
				"z" : -19
			},
			"seller" : "K9us",
			"time" : "2019/02/03",
			"type" : "buy",
			"volume" : 7680,
			"world" : "world"
		},
		{
			"amount" : 1,
			"buyer" : "japanimator",
			"location" : 
			{
				"x" : -63,
				"y" : 63,
				"z" : 10
			},
			"seller" : "NullCase",
			"time" : "2019/02/03",
			"type" : "buy",
			"volume" : 120,
			"world" : "world"
		},
		{
			"amount" : 26,
			"buyer" : "NullCase",
			"location" : 
			{
				"x" : -63,
				"y" : 63,
				"z" : 10
			},
			"seller" : "japanimator",
			"time" : "2019/02/04",
			"type" : "sell",
			"volume" : 2860,
			"world" : "world"
		},
		{
			"amount" : 62,
			"buyer" : "NullCase",
			"location" : 
			{
				"x" : -63,
				"y" : 64,
				"z" : 10
			},
			"seller" : "japanimator",
			"time" : "2019/02/04",
			"type" : "sell",
			"volume" : 3596,
			"world" : "world"
		},
		{
			"amount" : 64,
			"buyer" : "NullCase",
			"location" : 
			{
				"x" : -63,
				"y" : 64,
				"z" : 10
			},
			"seller" : "japanimator",
			"time" : "2019/02/05",
			"type" : "sell",
			"volume" : 3712,
			"world" : "world"
		},
		{
			"amount" : 1,
			"buyer" : "__Tilt",
			"location" : 
			{
				"x" : 37,
				"y" : 63,
				"z" : -19
			},
			"seller" : "K9us",
			"time" : "2019/02/05",
			"type" : "buy",
			"volume" : 120,
			"world" : "world"
		},
		{
			"amount" : 3,
			"buyer" : "japanimator",
			"location" : 
			{
				"x" : -63,
				"y" : 63,
				"z" : 10
			},
			"seller" : "NullCase",
			"time" : "2019/02/06",
			"type" : "buy",
			"volume" : 372,
			"world" : "world"
		},
		{
			"amount" : 2,
			"buyer" : "Stormrunners",
			"location" : 
			{
				"x" : 37,
				"y" : 63,
				"z" : -19
			},
			"seller" : "K9us",
			"time" : "2019/02/07",
			"type" : "buy",
			"volume" : 240,
			"world" : "world"
		},
		{
			"amount" : 1,
			"buyer" : "japanimator",
			"location" : 
			{
				"x" : -63,
				"y" : 63,
				"z" : 10
			},
			"seller" : "NullCase",
			"time" : "2019/02/07",
			"type" : "buy",
			"volume" : 124,
			"world" : "world"
		},
		{
			"amount" : 1,
			"buyer" : "Stormrunners",
			"location" : 
			{
				"x" : 37,
				"y" : 63,
				"z" : -19
			},
			"seller" : "K9us",
			"time" : "2019/02/08",
			"type" : "buy",
			"volume" : 120,
			"world" : "world"
		},
		{
			"amount" : 10,
			"buyer" : "Aewheros",
			"location" : 
			{
				"x" : -63,
				"y" : 63,
				"z" : 10
			},
			"seller" : "NullCase",
			"time" : "2019/02/10",
			"type" : "buy",
			"volume" : 1240,
			"world" : "world"
		},
		{
			"amount" : 1,
			"buyer" : "Stormrunners",
			"location" : 
			{
				"x" : 37,
				"y" : 63,
				"z" : -19
			},
			"seller" : "K9us",
			"time" : "2019/02/11",
			"type" : "buy",
			"volume" : 120,
			"world" : "world"
		},
		{
			"amount" : 1,
			"buyer" : "japanimator",
			"location" : 
			{
				"x" : -63,
				"y" : 63,
				"z" : 10
			},
			"seller" : "NullCase",
			"time" : "2019/02/12",
			"type" : "buy",
			"volume" : 124,
			"world" : "world"
		},
		{
			"amount" : 192,
			"buyer" : "NullCase",
			"location" : 
			{
				"x" : -63,
				"y" : 64,
				"z" : 10
			},
			"seller" : "japanimator",
			"time" : "2019/02/12",
			"type" : "sell",
			"volume" : 11136,
			"world" : "world"
		},
		{
			"amount" : 5,
			"buyer" : "__Tilt",
			"location" : 
			{
				"x" : -63,
				"y" : 64,
				"z" : 10
			},
			"seller" : "NullCase",
			"time" : "2019/02/13",
			"type" : "buy",
			"volume" : 320,
			"world" : "world"
		},
		{
			"amount" : 1,
			"buyer" : "Miljanee",
			"location" : 
			{
				"x" : 40,
				"y" : 63,
				"z" : -18
			},
			"seller" : "K9us",
			"time" : "2019/02/14",
			"type" : "buy",
			"volume" : 120,
			"world" : "world"
		},
		{
			"amount" : 4,
			"buyer" : "Stormrunners",
			"location" : 
			{
				"x" : -63,
				"y" : 64,
				"z" : 10
			},
			"seller" : "NullCase",
			"time" : "2019/02/14",
			"type" : "buy",
			"volume" : 256,
			"world" : "world"
		},
		{
			"amount" : 3,
			"buyer" : "K9us",
			"location" : 
			{
				"x" : 40,
				"y" : 63,
				"z" : -18
			},
			"seller" : "Stormrunners",
			"time" : "2019/02/14",
			"type" : "sell",
			"volume" : 345,
			"world" : "world"
		},
		{
			"amount" : 2,
			"buyer" : "__Tilt",
			"location" : 
			{
				"x" : -63,
				"y" : 64,
				"z" : 10
			},
			"seller" : "NullCase",
			"time" : "2019/02/16",
			"type" : "buy",
			"volume" : 128,
			"world" : "world"
		},
		{
			"amount" : 1,
			"buyer" : "NullCase",
			"location" : 
			{
				"x" : -63,
				"y" : 64,
				"z" : 10
			},
			"seller" : "__Tilt",
			"time" : "2019/02/16",
			"type" : "sell",
			"volume" : 58,
			"world" : "world"
		},
		{
			"amount" : 1,
			"buyer" : "coconewell92",
			"location" : 
			{
				"x" : 269,
				"y" : 3,
				"z" : -5
			},
			"seller" : "Cardano_ff",
			"time" : "2019/02/17",
			"type" : "buy",
			"volume" : 1000,
			"world" : "world_the_end"
		},
		{
			"amount" : 296,
			"buyer" : "K9us",
			"location" : 
			{
				"x" : -63,
				"y" : 64,
				"z" : 10
			},
			"seller" : "NullCase",
			"time" : "2019/02/20",
			"type" : "buy",
			"volume" : 18944,
			"world" : "world"
		},
		{
			"amount" : 106,
			"buyer" : "AshGreninja2579",
			"location" : 
			{
				"x" : -63,
				"y" : 63,
				"z" : 10
			},
			"seller" : "NullCase",
			"time" : "2019/02/20",
			"type" : "buy",
			"volume" : 13144,
			"world" : "world"
		},
		{
			"amount" : 1,
			"buyer" : "coconewell92",
			"location" : 
			{
				"x" : 269,
				"y" : 3,
				"z" : -5
			},
			"seller" : "Cardano_ff",
			"time" : "2019/02/21",
			"type" : "buy",
			"volume" : 1000,
			"world" : "world_the_end"
		},
		{
			"amount" : 1,
			"buyer" : "EnDristON",
			"location" : 
			{
				"x" : -63,
				"y" : 63,
				"z" : 10
			},
			"seller" : "NullCase",
			"time" : "2019/02/22",
			"type" : "buy",
			"volume" : 124,
			"world" : "world"
		},
		{
			"amount" : 1,
			"buyer" : "__Tilt",
			"location" : 
			{
				"x" : -63,
				"y" : 63,
				"z" : 10
			},
			"seller" : "NullCase",
			"time" : "2019/02/25",
			"type" : "buy",
			"volume" : 124,
			"world" : "world"
		},
		{
			"amount" : 15,
			"buyer" : "__Tilt",
			"location" : 
			{
				"x" : 40,
				"y" : 63,
				"z" : -18
			},
			"seller" : "K9us",
			"time" : "2019/02/26",
			"type" : "buy",
			"volume" : 1800,
			"world" : "world"
		},
		{
			"amount" : 8,
			"buyer" : "__Tilt",
			"location" : 
			{
				"x" : 60,
				"y" : 71,
				"z" : -17
			},
			"seller" : "K9us",
			"time" : "2019/02/26",
			"type" : "buy",
			"volume" : 960,
			"world" : "world"
		},
		{
			"amount" : 4,
			"buyer" : "coconewell92",
			"location" : 
			{
				"x" : 269,
				"y" : 3,
				"z" : -5
			},
			"seller" : "Cardano_ff",
			"time" : "2019/02/26",
			"type" : "buy",
			"volume" : 4000,
			"world" : "world_the_end"
		},
		{
			"amount" : 2,
			"buyer" : "Vallenius",
			"location" : 
			{
				"x" : -63,
				"y" : 63,
				"z" : 10
			},
			"seller" : "NullCase",
			"time" : "2019/02/27",
			"type" : "buy",
			"volume" : 248,
			"world" : "world"
		},
		{
			"amount" : 6,
			"buyer" : "EnDristON",
			"location" : 
			{
				"x" : -63,
				"y" : 63,
				"z" : 10
			},
			"seller" : "NullCase",
			"time" : "2019/02/27",
			"type" : "buy",
			"volume" : 744,
			"world" : "world"
		},
		{
			"amount" : 2,
			"buyer" : "Vallenius",
			"location" : 
			{
				"x" : -63,
				"y" : 63,
				"z" : 10
			},
			"seller" : "NullCase",
			"time" : "2019/03/05",
			"type" : "buy",
			"volume" : 390,
			"world" : "world"
		},
		{
			"amount" : 3,
			"buyer" : "Remixster",
			"location" : 
			{
				"x" : -63,
				"y" : 63,
				"z" : 10
			},
			"seller" : "NullCase",
			"time" : "2019/03/06",
			"type" : "buy",
			"volume" : 585,
			"world" : "world"
		},
		{
			"amount" : 6,
			"buyer" : "NullCase",
			"location" : 
			{
				"x" : -63,
				"y" : 63,
				"z" : 10
			},
			"seller" : "japanimator",
			"time" : "2019/03/09",
			"type" : "sell",
			"volume" : 1062,
			"world" : "world"
		},
		{
			"amount" : 1,
			"buyer" : "Vallenius",
			"location" : 
			{
				"x" : -63,
				"y" : 63,
				"z" : 10
			},
			"seller" : "NullCase",
			"time" : "2019/03/10",
			"type" : "buy",
			"volume" : 195,
			"world" : "world"
		},
		{
			"amount" : 64,
			"buyer" : "coconewell92",
			"location" : 
			{
				"x" : 40,
				"y" : 63,
				"z" : -18
			},
			"seller" : "K9us",
			"time" : "2019/03/12",
			"type" : "buy",
			"volume" : 7680,
			"world" : "world"
		},
		{
			"amount" : 54,
			"buyer" : "NullCase",
			"location" : 
			{
				"x" : -63,
				"y" : 63,
				"z" : 10
			},
			"seller" : "coconewell92",
			"time" : "2019/03/17",
			"type" : "sell",
			"volume" : 9558,
			"world" : "world"
		},
		{
			"amount" : 861,
			"buyer" : "NullCase",
			"location" : 
			{
				"x" : -63,
				"y" : 64,
				"z" : 10
			},
			"seller" : "coconewell92",
			"time" : "2019/03/17",
			"type" : "sell",
			"volume" : 94710,
			"world" : "world"
		},
		{
			"amount" : 15,
			"buyer" : "dandenoth",
			"location" : 
			{
				"x" : 269,
				"y" : 3,
				"z" : -5
			},
			"seller" : "Cardano_ff",
			"time" : "2019/03/18",
			"type" : "buy",
			"volume" : 15000,
			"world" : "world_the_end"
		},
		{
			"amount" : 64,
			"buyer" : "NullCase",
			"location" : 
			{
				"x" : -63,
				"y" : 64,
				"z" : 10
			},
			"seller" : "japanimator",
			"time" : "2019/03/19",
			"type" : "sell",
			"volume" : 7040,
			"world" : "world"
		},
		{
			"amount" : 384,
			"buyer" : "Vallenius",
			"location" : 
			{
				"x" : -63,
				"y" : 64,
				"z" : 10
			},
			"seller" : "NullCase",
			"time" : "2019/03/20",
			"type" : "buy",
			"volume" : 49920,
			"world" : "world"
		},
		{
			"amount" : 1,
			"buyer" : "Stormrunners",
			"location" : 
			{
				"x" : 40,
				"y" : 63,
				"z" : -18
			},
			"seller" : "K9us",
			"time" : "2019/03/21",
			"type" : "buy",
			"volume" : 120,
			"world" : "world"
		},
		{
			"amount" : 1,
			"buyer" : "coconewell92",
			"location" : 
			{
				"x" : 269,
				"y" : 3,
				"z" : -5
			},
			"seller" : "Cardano_ff",
			"time" : "2019/03/25",
			"type" : "buy",
			"volume" : 1000,
			"world" : "world_the_end"
		},
		{
			"amount" : 1,
			"buyer" : "TxAggieMc",
			"location" : 
			{
				"x" : 60,
				"y" : 71,
				"z" : -17
			},
			"seller" : "K9us",
			"time" : "2019/03/26",
			"type" : "buy",
			"volume" : 120,
			"world" : "world"
		},
		{
			"amount" : 1,
			"buyer" : "dandenoth",
			"location" : 
			{
				"x" : 269,
				"y" : 3,
				"z" : -5
			},
			"seller" : "Cardano_ff",
			"time" : "2019/03/26",
			"type" : "buy",
			"volume" : 1000,
			"world" : "world_the_end"
		},
		{
			"amount" : 4,
			"buyer" : "Stormrunners",
			"location" : 
			{
				"x" : 40,
				"y" : 63,
				"z" : -18
			},
			"seller" : "K9us",
			"time" : "2019/03/27",
			"type" : "buy",
			"volume" : 480,
			"world" : "world"
		},
		{
			"amount" : 1,
			"buyer" : "darkraysplash",
			"location" : 
			{
				"x" : -63,
				"y" : 64,
				"z" : 10
			},
			"seller" : "NullCase",
			"time" : "2019/03/28",
			"type" : "buy",
			"volume" : 130,
			"world" : "world"
		},
		{
			"amount" : 1,
			"buyer" : "NullCase",
			"location" : 
			{
				"x" : -63,
				"y" : 64,
				"z" : 10
			},
			"seller" : "darkraysplash",
			"time" : "2019/03/28",
			"type" : "sell",
			"volume" : 110,
			"world" : "world"
		},
		{
			"amount" : 1,
			"buyer" : "Stormrunners",
			"location" : 
			{
				"x" : 40,
				"y" : 63,
				"z" : -18
			},
			"seller" : "K9us",
			"time" : "2019/03/29",
			"type" : "buy",
			"volume" : 120,
			"world" : "world"
		},
		{
			"amount" : 2,
			"buyer" : "Stormrunners",
			"location" : 
			{
				"x" : -63,
				"y" : 64,
				"z" : 10
			},
			"seller" : "NullCase",
			"time" : "2019/03/29",
			"type" : "buy",
			"volume" : 260,
			"world" : "world"
		},
		{
			"amount" : 1,
			"buyer" : "NullCase",
			"location" : 
			{
				"x" : -63,
				"y" : 64,
				"z" : 10
			},
			"seller" : "coconewell92",
			"time" : "2019/04/05",
			"type" : "sell",
			"volume" : 110,
			"world" : "world"
		},
		{
			"amount" : 703,
			"buyer" : "K9us",
			"location" : 
			{
				"x" : 40,
				"y" : 63,
				"z" : -18
			},
			"seller" : "coconewell92",
			"time" : "2019/04/05",
			"type" : "sell",
			"volume" : 80845,
			"world" : "world"
		},
		{
			"amount" : 10,
			"buyer" : "dandenoth",
			"location" : 
			{
				"x" : 269,
				"y" : 3,
				"z" : -5
			},
			"seller" : "Cardano_ff",
			"time" : "2019/04/06",
			"type" : "buy",
			"volume" : 10000,
			"world" : "world_the_end"
		},
		{
			"amount" : 1,
			"buyer" : "AshGreninja2579",
			"location" : 
			{
				"x" : -63,
				"y" : 64,
				"z" : 10
			},
			"seller" : "NullCase",
			"time" : "2019/04/08",
			"type" : "buy",
			"volume" : 130,
			"world" : "world"
		},
		{
			"amount" : 1,
			"buyer" : "Technerd05",
			"location" : 
			{
				"x" : 40,
				"y" : 63,
				"z" : -18
			},
			"seller" : "K9us",
			"time" : "2019/04/13",
			"type" : "buy",
			"volume" : 120,
			"world" : "world"
		},
		{
			"amount" : 6,
			"buyer" : "Technerd05",
			"location" : 
			{
				"x" : -333,
				"y" : 71,
				"z" : -476
			},
			"seller" : "EnDristON",
			"time" : "2019/04/14",
			"type" : "buy",
			"volume" : 720,
			"world" : "world"
		},
		{
			"amount" : 3,
			"buyer" : "EnDristON",
			"location" : 
			{
				"x" : 40,
				"y" : 63,
				"z" : -18
			},
			"seller" : "K9us",
			"time" : "2019/04/15",
			"type" : "buy",
			"volume" : 360,
			"world" : "world"
		},
		{
			"amount" : 6,
			"buyer" : "Mathemagician4",
			"location" : 
			{
				"x" : -63,
				"y" : 64,
				"z" : 10
			},
			"seller" : "NullCase",
			"time" : "2019/04/17",
			"type" : "buy",
			"volume" : 780,
			"world" : "world"
		},
		{
			"amount" : 64,
			"buyer" : "dandenoth",
			"location" : 
			{
				"x" : 269,
				"y" : 3,
				"z" : -5
			},
			"seller" : "Cardano_ff",
			"time" : "2019/04/22",
			"type" : "buy",
			"volume" : 64000,
			"world" : "world_the_end"
		},
		{
			"amount" : 114,
			"buyer" : "NullCase",
			"location" : 
			{
				"x" : -63,
				"y" : 64,
				"z" : 10
			},
			"seller" : "sparkXstorm",
			"time" : "2019/04/26",
			"type" : "sell",
			"volume" : 12540,
			"world" : "world"
		},
		{
			"amount" : 490,
			"buyer" : "K9us",
			"location" : 
			{
				"x" : 40,
				"y" : 63,
				"z" : -18
			},
			"seller" : "sparkXstorm",
			"time" : "2019/04/27",
			"type" : "sell",
			"volume" : 56350,
			"world" : "world"
		},
		{
			"amount" : 105,
			"buyer" : "K9us",
			"location" : 
			{
				"x" : 40,
				"y" : 63,
				"z" : -18
			},
			"seller" : "sparkXstorm",
			"time" : "2019/04/28",
			"type" : "sell",
			"volume" : 12075,
			"world" : "world"
		},
		{
			"amount" : 46,
			"buyer" : "K9us",
			"location" : 
			{
				"x" : 60,
				"y" : 71,
				"z" : -17
			},
			"seller" : "sparkXstorm",
			"time" : "2019/04/28",
			"type" : "sell",
			"volume" : 5290,
			"world" : "world"
		},
		{
			"amount" : 192,
			"buyer" : "K9us",
			"location" : 
			{
				"x" : 40,
				"y" : 63,
				"z" : -18
			},
			"seller" : "sparkXstorm",
			"time" : "2019/04/28",
			"type" : "sell",
			"volume" : 22080,
			"world" : "world"
		},
		{
			"amount" : 1,
			"buyer" : "AshGreninja2579",
			"location" : 
			{
				"x" : 40,
				"y" : 63,
				"z" : -18
			},
			"seller" : "K9us",
			"time" : "2019/04/28",
			"type" : "buy",
			"volume" : 120,
			"world" : "world"
		},
		{
			"amount" : 1,
			"buyer" : "NullCase",
			"location" : 
			{
				"x" : -63,
				"y" : 64,
				"z" : 10
			},
			"seller" : "EnDristON",
			"time" : "2019/04/29",
			"type" : "sell",
			"volume" : 110,
			"world" : "world"
		},
		{
			"amount" : 1,
			"buyer" : "EnDristON",
			"location" : 
			{
				"x" : -63,
				"y" : 64,
				"z" : 10
			},
			"seller" : "NullCase",
			"time" : "2019/04/29",
			"type" : "buy",
			"volume" : 130,
			"world" : "world"
		},
		{
			"amount" : 1,
			"buyer" : "AshGreninja2579",
			"location" : 
			{
				"x" : -63,
				"y" : 64,
				"z" : 10
			},
			"seller" : "NullCase",
			"time" : "2019/05/01",
			"type" : "buy",
			"volume" : 130,
			"world" : "world"
		},
		{
			"amount" : 2,
			"buyer" : "EnDristON",
			"location" : 
			{
				"x" : -63,
				"y" : 64,
				"z" : 10
			},
			"seller" : "NullCase",
			"time" : "2019/05/02",
			"type" : "buy",
			"volume" : 260,
			"world" : "world"
		},
		{
			"amount" : 1,
			"buyer" : "coconewell92",
			"location" : 
			{
				"x" : 269,
				"y" : 3,
				"z" : -5
			},
			"seller" : "Cardano_ff",
			"time" : "2019/05/03",
			"type" : "buy",
			"volume" : 1000,
			"world" : "world_the_end"
		},
		{
			"amount" : 343,
			"buyer" : "K9us",
			"location" : 
			{
				"x" : 40,
				"y" : 63,
				"z" : -18
			},
			"seller" : "sparkXstorm",
			"time" : "2019/05/03",
			"type" : "sell",
			"volume" : 39445,
			"world" : "world"
		},
		{
			"amount" : 2,
			"buyer" : "sparkXstorm",
			"location" : 
			{
				"x" : -63,
				"y" : 64,
				"z" : 10
			},
			"seller" : "NullCase",
			"time" : "2019/05/03",
			"type" : "buy",
			"volume" : 260,
			"world" : "world"
		},
		{
			"amount" : 106,
			"buyer" : "K9us",
			"location" : 
			{
				"x" : 40,
				"y" : 63,
				"z" : -18
			},
			"seller" : "sparkXstorm",
			"time" : "2019/05/03",
			"type" : "sell",
			"volume" : 12190,
			"world" : "world"
		},
		{
			"amount" : 1,
			"buyer" : "Pancen",
			"location" : 
			{
				"x" : -63,
				"y" : 64,
				"z" : 10
			},
			"seller" : "NullCase",
			"time" : "2019/05/04",
			"type" : "buy",
			"volume" : 130,
			"world" : "world"
		},
		{
			"amount" : 1,
			"buyer" : "NullCase",
			"location" : 
			{
				"x" : -63,
				"y" : 64,
				"z" : 10
			},
			"seller" : "Pancen",
			"time" : "2019/05/04",
			"type" : "sell",
			"volume" : 110,
			"world" : "world"
		},
		{
			"amount" : 1731,
			"buyer" : "NullCase",
			"location" : 
			{
				"x" : -63,
				"y" : 64,
				"z" : 10
			},
			"seller" : "Pancen",
			"time" : "2019/05/06",
			"type" : "sell",
			"volume" : 190410,
			"world" : "world"
		},
		{
			"amount" : 2,
			"buyer" : "Pancen",
			"location" : 
			{
				"x" : -63,
				"y" : 64,
				"z" : 10
			},
			"seller" : "NullCase",
			"time" : "2019/05/06",
			"type" : "buy",
			"volume" : 260,
			"world" : "world"
		},
		{
			"amount" : 275,
			"buyer" : "K9us",
			"location" : 
			{
				"x" : 40,
				"y" : 63,
				"z" : -18
			},
			"seller" : "Pancen",
			"time" : "2019/05/06",
			"type" : "sell",
			"volume" : 31625,
			"world" : "world"
		},
		{
			"amount" : 5,
			"buyer" : "Pancen",
			"location" : 
			{
				"x" : -63,
				"y" : 64,
				"z" : 10
			},
			"seller" : "NullCase",
			"time" : "2019/05/08",
			"type" : "buy",
			"volume" : 650,
			"world" : "world"
		},
		{
			"amount" : 1,
			"buyer" : "Serpentcraft",
			"location" : 
			{
				"x" : 40,
				"y" : 63,
				"z" : -18
			},
			"seller" : "K9us",
			"time" : "2019/05/11",
			"type" : "buy",
			"volume" : 120,
			"world" : "world"
		},
		{
			"amount" : 3,
			"buyer" : "daboogaoogaman",
			"location" : 
			{
				"x" : -63,
				"y" : 64,
				"z" : 10
			},
			"seller" : "NullCase",
			"time" : "2019/05/11",
			"type" : "buy",
			"volume" : 390,
			"world" : "world"
		},
		{
			"amount" : 9,
			"buyer" : "EnDristON",
			"location" : 
			{
				"x" : 40,
				"y" : 63,
				"z" : -18
			},
			"seller" : "K9us",
			"time" : "2019/05/24",
			"type" : "buy",
			"volume" : 1080,
			"world" : "world"
		},
		{
			"amount" : 4,
			"buyer" : "K9us",
			"location" : 
			{
				"x" : 40,
				"y" : 63,
				"z" : -18
			},
			"seller" : "pepparkaksgubbe",
			"time" : "2019/06/09",
			"type" : "sell",
			"volume" : 460,
			"world" : "world"
		},
		{
			"amount" : 3,
			"buyer" : "Aewheros",
			"location" : 
			{
				"x" : -63,
				"y" : 64,
				"z" : 10
			},
			"seller" : "NullCase",
			"time" : "2019/06/12",
			"type" : "buy",
			"volume" : 390,
			"world" : "world"
		},
		{
			"amount" : 2,
			"buyer" : "NullCase",
			"location" : 
			{
				"x" : -63,
				"y" : 64,
				"z" : 10
			},
			"seller" : "Aewheros",
			"time" : "2019/06/12",
			"type" : "sell",
			"volume" : 220,
			"world" : "world"
		},
		{
			"amount" : 7,
			"buyer" : "Oaken_Ralph",
			"location" : 
			{
				"x" : -63,
				"y" : 64,
				"z" : 10
			},
			"seller" : "NullCase",
			"time" : "2019/06/13",
			"type" : "buy",
			"volume" : 910,
			"world" : "world"
		},
		{
			"amount" : 21,
			"buyer" : "K9us",
			"location" : 
			{
				"x" : 40,
				"y" : 63,
				"z" : -18
			},
			"seller" : "sparkXstorm",
			"time" : "2019/06/14",
			"type" : "sell",
			"volume" : 2415,
			"world" : "world"
		},
		{
			"amount" : 18,
			"buyer" : "NullCase",
			"location" : 
			{
				"x" : -63,
				"y" : 64,
				"z" : 10
			},
			"seller" : "japanimator",
			"time" : "2019/06/14",
			"type" : "sell",
			"volume" : 1980,
			"world" : "world"
		},
		{
			"amount" : 46,
			"buyer" : "NullCase",
			"location" : 
			{
				"x" : -63,
				"y" : 65,
				"z" : 10
			},
			"seller" : "japanimator",
			"time" : "2019/06/14",
			"type" : "sell",
			"volume" : 3450,
			"world" : "world"
		},
		{
			"amount" : 64,
			"buyer" : "K9us",
			"location" : 
			{
				"x" : 40,
				"y" : 63,
				"z" : -18
			},
			"seller" : "sparkXstorm",
			"time" : "2019/06/14",
			"type" : "sell",
			"volume" : 7360,
			"world" : "world"
		},
		{
			"amount" : 64,
			"buyer" : "NiCe69",
			"location" : 
			{
				"x" : -63,
				"y" : 64,
				"z" : 10
			},
			"seller" : "NullCase",
			"time" : "2019/06/15",
			"type" : "buy",
			"volume" : 8320,
			"world" : "world"
		},
		{
			"amount" : 6,
			"buyer" : "NullCase",
			"location" : 
			{
				"x" : -63,
				"y" : 65,
				"z" : 10
			},
			"seller" : "sparkXstorm",
			"time" : "2019/06/17",
			"type" : "sell",
			"volume" : 450,
			"world" : "world"
		},
		{
			"amount" : 12,
			"buyer" : "NullCase",
			"location" : 
			{
				"x" : -63,
				"y" : 64,
				"z" : 10
			},
			"seller" : "sparkXstorm",
			"time" : "2019/06/17",
			"type" : "sell",
			"volume" : 1320,
			"world" : "world"
		},
		{
			"amount" : 73,
			"buyer" : "NullCase",
			"location" : 
			{
				"x" : -63,
				"y" : 65,
				"z" : 10
			},
			"seller" : "sparkXstorm",
			"time" : "2019/06/18",
			"type" : "sell",
			"volume" : 5475,
			"world" : "world"
		},
		{
			"amount" : 39,
			"buyer" : "NullCase",
			"location" : 
			{
				"x" : -63,
				"y" : 65,
				"z" : 10
			},
			"seller" : "sparkXstorm",
			"time" : "2019/06/20",
			"type" : "sell",
			"volume" : 2925,
			"world" : "world"
		},
		{
			"amount" : 1,
			"buyer" : "RyanJG",
			"location" : 
			{
				"x" : 51,
				"y" : 72,
				"z" : -6
			},
			"seller" : "K9us",
			"time" : "2019/06/21",
			"type" : "buy",
			"volume" : 79,
			"world" : "world"
		},
		{
			"amount" : 65,
			"buyer" : "pepparkaksgubbe",
			"location" : 
			{
				"x" : 51,
				"y" : 72,
				"z" : -6
			},
			"seller" : "K9us",
			"time" : "2019/06/23",
			"type" : "buy",
			"volume" : 5135,
			"world" : "world"
		},
		{
			"amount" : 3,
			"buyer" : "NullCase",
			"location" : 
			{
				"x" : -63,
				"y" : 65,
				"z" : 10
			},
			"seller" : "sparkXstorm",
			"time" : "2019/06/28",
			"type" : "sell",
			"volume" : 225,
			"world" : "world"
		},
		{
			"amount" : 129,
			"buyer" : "NullCase",
			"location" : 
			{
				"x" : -63,
				"y" : 65,
				"z" : 10
			},
			"seller" : "sparkXstorm",
			"time" : "2019/06/30",
			"type" : "sell",
			"volume" : 9675,
			"world" : "world"
		},
		{
			"amount" : 1,
			"buyer" : "jackcam6",
			"location" : 
			{
				"x" : 33,
				"y" : 52,
				"z" : -44
			},
			"seller" : "K9us",
			"time" : "2019/07/01",
			"type" : "buy",
			"volume" : 79,
			"world" : "world"
		},
		{
			"amount" : 2,
			"buyer" : "NullCase",
			"location" : 
			{
				"x" : -63,
				"y" : 65,
				"z" : 10
			},
			"seller" : "sparkXstorm",
			"time" : "2019/07/01",
			"type" : "sell",
			"volume" : 150,
			"world" : "world"
		},
		{
			"amount" : 12,
			"buyer" : "NullCase",
			"location" : 
			{
				"x" : -63,
				"y" : 65,
				"z" : 10
			},
			"seller" : "sparkXstorm",
			"time" : "2019/07/02",
			"type" : "sell",
			"volume" : 900,
			"world" : "world"
		},
		{
			"amount" : 135,
			"buyer" : "K9us",
			"location" : 
			{
				"x" : 33,
				"y" : 52,
				"z" : -44
			},
			"seller" : "sparkXstorm",
			"time" : "2019/07/03",
			"type" : "sell",
			"volume" : 9450,
			"world" : "world"
		},
		{
			"amount" : 194,
			"buyer" : "Vallenius",
			"location" : 
			{
				"x" : -63,
				"y" : 65,
				"z" : 10
			},
			"seller" : "NullCase",
			"time" : "2019/07/03",
			"type" : "buy",
			"volume" : 15326,
			"world" : "world"
		},
		{
			"amount" : 316,
			"buyer" : "Vallenius",
			"location" : 
			{
				"x" : -63,
				"y" : 64,
				"z" : 10
			},
			"seller" : "NullCase",
			"time" : "2019/07/03",
			"type" : "buy",
			"volume" : 41080,
			"world" : "world"
		},
		{
			"amount" : 75,
			"buyer" : "NullCase",
			"location" : 
			{
				"x" : -63,
				"y" : 64,
				"z" : 10
			},
			"seller" : "sparkXstorm",
			"time" : "2019/07/04",
			"type" : "sell",
			"volume" : 8250,
			"world" : "world"
		},
		{
			"amount" : 1,
			"buyer" : "Vivifoxx",
			"location" : 
			{
				"x" : -63,
				"y" : 63,
				"z" : 10
			},
			"seller" : "NullCase",
			"time" : "2019/07/05",
			"type" : "buy",
			"volume" : 195,
			"world" : "world"
		},
		{
			"amount" : 1,
			"buyer" : "K9us",
			"location" : 
			{
				"x" : 33,
				"y" : 52,
				"z" : -44
			},
			"seller" : "Vivifoxx",
			"time" : "2019/07/05",
			"type" : "sell",
			"volume" : 70,
			"world" : "world"
		},
		{
			"amount" : 1,
			"buyer" : "Vivifoxx",
			"location" : 
			{
				"x" : 33,
				"y" : 52,
				"z" : -44
			},
			"seller" : "K9us",
			"time" : "2019/07/05",
			"type" : "buy",
			"volume" : 79,
			"world" : "world"
		},
		{
			"amount" : 102,
			"buyer" : "NullCase",
			"location" : 
			{
				"x" : -63,
				"y" : 64,
				"z" : 10
			},
			"seller" : "sparkXstorm",
			"time" : "2019/07/05",
			"type" : "sell",
			"volume" : 11220,
			"world" : "world"
		},
		{
			"amount" : 1216,
			"buyer" : "Vallenius",
			"location" : 
			{
				"x" : 33,
				"y" : 52,
				"z" : -44
			},
			"seller" : "K9us",
			"time" : "2019/07/06",
			"type" : "buy",
			"volume" : 96064,
			"world" : "world"
		},
		{
			"amount" : 2,
			"buyer" : "pepparkaksgubbe",
			"location" : 
			{
				"x" : -63,
				"y" : 64,
				"z" : 10
			},
			"seller" : "NullCase",
			"time" : "2019/07/08",
			"type" : "buy",
			"volume" : 260,
			"world" : "world"
		},
		{
			"amount" : 384,
			"buyer" : "sparkXstorm",
			"location" : 
			{
				"x" : 33,
				"y" : 52,
				"z" : -44
			},
			"seller" : "K9us",
			"time" : "2019/07/09",
			"type" : "buy",
			"volume" : 30336,
			"world" : "world"
		},
		{
			"amount" : 191,
			"buyer" : "NullCase",
			"location" : 
			{
				"x" : -63,
				"y" : 64,
				"z" : 10
			},
			"seller" : "sparkXstorm",
			"time" : "2019/07/09",
			"type" : "sell",
			"volume" : 21010,
			"world" : "world"
		},
		{
			"amount" : 193,
			"buyer" : "NullCase",
			"location" : 
			{
				"x" : -63,
				"y" : 65,
				"z" : 10
			},
			"seller" : "sparkXstorm",
			"time" : "2019/07/09",
			"type" : "sell",
			"volume" : 14475,
			"world" : "world"
		},
		{
			"amount" : 1,
			"buyer" : "Mathemagician4",
			"location" : 
			{
				"x" : -63,
				"y" : 65,
				"z" : 10
			},
			"seller" : "NullCase",
			"time" : "2019/07/11",
			"type" : "buy",
			"volume" : 79,
			"world" : "world"
		},
		{
			"amount" : 546,
			"buyer" : "NullCase",
			"location" : 
			{
				"x" : -63,
				"y" : 65,
				"z" : 10
			},
			"seller" : "sparkXstorm",
			"time" : "2019/07/12",
			"type" : "sell",
			"volume" : 40950,
			"world" : "world"
		},
		{
			"amount" : 64,
			"buyer" : "Dredhounds",
			"location" : 
			{
				"x" : -63,
				"y" : 65,
				"z" : 10
			},
			"seller" : "NullCase",
			"time" : "2019/07/14",
			"type" : "buy",
			"volume" : 5056,
			"world" : "world"
		},
		{
			"amount" : 21,
			"buyer" : "NullCase",
			"location" : 
			{
				"x" : -63,
				"y" : 65,
				"z" : 10
			},
			"seller" : "sparkXstorm",
			"time" : "2019/07/14",
			"type" : "sell",
			"volume" : 1575,
			"world" : "world"
		},
		{
			"amount" : 1,
			"buyer" : "Dredhounds",
			"location" : 
			{
				"x" : -63,
				"y" : 65,
				"z" : 10
			},
			"seller" : "NullCase",
			"time" : "2019/07/14",
			"type" : "buy",
			"volume" : 79,
			"world" : "world"
		},
		{
			"amount" : 64,
			"buyer" : "Dredhounds",
			"location" : 
			{
				"x" : -63,
				"y" : 65,
				"z" : 10
			},
			"seller" : "NullCase",
			"time" : "2019/07/15",
			"type" : "buy",
			"volume" : 5056,
			"world" : "world"
		},
		{
			"amount" : 72,
			"buyer" : "Vallenius",
			"location" : 
			{
				"x" : -63,
				"y" : 65,
				"z" : 10
			},
			"seller" : "NullCase",
			"time" : "2019/07/18",
			"type" : "buy",
			"volume" : 5688,
			"world" : "world"
		},
		{
			"amount" : 59,
			"buyer" : "NullCase",
			"location" : 
			{
				"x" : -63,
				"y" : 65,
				"z" : 10
			},
			"seller" : "sparkXstorm",
			"time" : "2019/07/19",
			"type" : "sell",
			"volume" : 4425,
			"world" : "world"
		},
		{
			"amount" : 65,
			"buyer" : "Mathemagician4",
			"location" : 
			{
				"x" : -63,
				"y" : 65,
				"z" : 10
			},
			"seller" : "NullCase",
			"time" : "2019/07/19",
			"type" : "buy",
			"volume" : 5135,
			"world" : "world"
		},
		{
			"amount" : 1,
			"buyer" : "Mathemagician4",
			"location" : 
			{
				"x" : 33,
				"y" : 52,
				"z" : -44
			},
			"seller" : "K9us",
			"time" : "2019/07/19",
			"type" : "buy",
			"volume" : 79,
			"world" : "world"
		},
		{
			"amount" : 2,
			"buyer" : "Mathemagician4",
			"location" : 
			{
				"x" : -63,
				"y" : 65,
				"z" : 10
			},
			"seller" : "NullCase",
			"time" : "2019/07/19",
			"type" : "buy",
			"volume" : 158,
			"world" : "world"
		},
		{
			"amount" : 104,
			"buyer" : "NullCase",
			"location" : 
			{
				"x" : -63,
				"y" : 65,
				"z" : 10
			},
			"seller" : "sparkXstorm",
			"time" : "2019/07/19",
			"type" : "sell",
			"volume" : 7800,
			"world" : "world"
		},
		{
			"amount" : 2,
			"buyer" : "sparkXstorm",
			"location" : 
			{
				"x" : -63,
				"y" : 65,
				"z" : 10
			},
			"seller" : "NullCase",
			"time" : "2019/07/20",
			"type" : "buy",
			"volume" : 158,
			"world" : "world"
		},
		{
			"amount" : 7,
			"buyer" : "Mathemagician4",
			"location" : 
			{
				"x" : -63,
				"y" : 65,
				"z" : 10
			},
			"seller" : "NullCase",
			"time" : "2019/07/21",
			"type" : "buy",
			"volume" : 553,
			"world" : "world"
		},
		{
			"amount" : 7,
			"buyer" : "NullCase",
			"location" : 
			{
				"x" : -63,
				"y" : 65,
				"z" : 10
			},
			"seller" : "sparkXstorm",
			"time" : "2019/07/22",
			"type" : "sell",
			"volume" : 525,
			"world" : "world"
		},
		{
			"amount" : 5,
			"buyer" : "Mathemagician4",
			"location" : 
			{
				"x" : -63,
				"y" : 65,
				"z" : 10
			},
			"seller" : "NullCase",
			"time" : "2019/07/22",
			"type" : "buy",
			"volume" : 395,
			"world" : "world"
		},
		{
			"amount" : 66,
			"buyer" : "Mathemagician4",
			"location" : 
			{
				"x" : -63,
				"y" : 65,
				"z" : 10
			},
			"seller" : "NullCase",
			"time" : "2019/07/25",
			"type" : "buy",
			"volume" : 5214,
			"world" : "world"
		},
		{
			"amount" : 53,
			"buyer" : "Oaken_Ralph",
			"location" : 
			{
				"x" : 33,
				"y" : 52,
				"z" : -44
			},
			"seller" : "K9us",
			"time" : "2019/07/25",
			"type" : "buy",
			"volume" : 4187,
			"world" : "world"
		},
		{
			"amount" : 37,
			"buyer" : "K9us",
			"location" : 
			{
				"x" : 33,
				"y" : 52,
				"z" : -44
			},
			"seller" : "Oaken_Ralph",
			"time" : "2019/07/25",
			"type" : "sell",
			"volume" : 2590,
			"world" : "world"
		},
		{
			"amount" : 128,
			"buyer" : "Vallenius",
			"location" : 
			{
				"x" : -63,
				"y" : 65,
				"z" : 10
			},
			"seller" : "NullCase",
			"time" : "2019/07/27",
			"type" : "buy",
			"volume" : 10112,
			"world" : "world"
		},
		{
			"amount" : 3,
			"buyer" : "Oaken_Ralph",
			"location" : 
			{
				"x" : -63,
				"y" : 65,
				"z" : 10
			},
			"seller" : "NullCase",
			"time" : "2019/07/27",
			"type" : "buy",
			"volume" : 237,
			"world" : "world"
		},
		{
			"amount" : 2,
			"buyer" : "Mathemagician4",
			"location" : 
			{
				"x" : -63,
				"y" : 64,
				"z" : 10
			},
			"seller" : "NullCase",
			"time" : "2019/07/27",
			"type" : "buy",
			"volume" : 260,
			"world" : "world"
		},
		{
			"amount" : 8,
			"buyer" : "NullCase",
			"location" : 
			{
				"x" : -63,
				"y" : 65,
				"z" : 10
			},
			"seller" : "sparkXstorm",
			"time" : "2019/07/27",
			"type" : "sell",
			"volume" : 600,
			"world" : "world"
		},
		{
			"amount" : 1,
			"buyer" : "Marcus265",
			"location" : 
			{
				"x" : 31,
				"y" : 52,
				"z" : -44
			},
			"seller" : "K9us",
			"time" : "2019/07/31",
			"type" : "buy",
			"volume" : 79,
			"world" : "world"
		},
		{
			"amount" : 12,
			"buyer" : "Oaken_Ralph",
			"location" : 
			{
				"x" : -63,
				"y" : 64,
				"z" : 10
			},
			"seller" : "NullCase",
			"time" : "2019/07/31",
			"type" : "buy",
			"volume" : 1560,
			"world" : "world"
		},
		{
			"amount" : 9,
			"buyer" : "Marcus265",
			"location" : 
			{
				"x" : 31,
				"y" : 52,
				"z" : -44
			},
			"seller" : "K9us",
			"time" : "2019/07/31",
			"type" : "buy",
			"volume" : 711,
			"world" : "world"
		},
		{
			"amount" : 1,
			"buyer" : "johsjohsjohs",
			"location" : 
			{
				"x" : -63,
				"y" : 64,
				"z" : 10
			},
			"seller" : "NullCase",
			"time" : "2019/08/06",
			"type" : "buy",
			"volume" : 130,
			"world" : "world"
		},
		{
			"amount" : 1,
			"buyer" : "johsjohsjohs",
			"location" : 
			{
				"x" : -63,
				"y" : 64,
				"z" : 10
			},
			"seller" : "NullCase",
			"time" : "2019/08/09",
			"type" : "buy",
			"volume" : 130,
			"world" : "world"
		},
		{
			"amount" : 27,
			"buyer" : "ezrone",
			"location" : 
			{
				"x" : 33,
				"y" : 52,
				"z" : -44
			},
			"seller" : "K9us",
			"time" : "2019/08/09",
			"type" : "buy",
			"volume" : 2133,
			"world" : "world"
		},
		{
			"amount" : 2,
			"buyer" : "johsjohsjohs",
			"location" : 
			{
				"x" : -63,
				"y" : 64,
				"z" : 10
			},
			"seller" : "NullCase",
			"time" : "2019/08/09",
			"type" : "buy",
			"volume" : 260,
			"world" : "world"
		},
		{
			"amount" : 65,
			"buyer" : "ezrone",
			"location" : 
			{
				"x" : -63,
				"y" : 64,
				"z" : 10
			},
			"seller" : "NullCase",
			"time" : "2019/08/11",
			"type" : "buy",
			"volume" : 8450,
			"world" : "world"
		},
		{
			"amount" : 1,
			"buyer" : "NullCase",
			"location" : 
			{
				"x" : -63,
				"y" : 63,
				"z" : 10
			},
			"seller" : "ezrone",
			"time" : "2019/08/11",
			"type" : "sell",
			"volume" : 177,
			"world" : "world"
		},
		{
			"amount" : 63,
			"buyer" : "NullCase",
			"location" : 
			{
				"x" : -63,
				"y" : 64,
				"z" : 10
			},
			"seller" : "ezrone",
			"time" : "2019/08/11",
			"type" : "sell",
			"volume" : 6930,
			"world" : "world"
		},
		{
			"amount" : 40,
			"buyer" : "ezrone",
			"location" : 
			{
				"x" : -63,
				"y" : 64,
				"z" : 10
			},
			"seller" : "NullCase",
			"time" : "2019/08/11",
			"type" : "buy",
			"volume" : 5200,
			"world" : "world"
		},
		{
			"amount" : 20,
			"buyer" : "ezrone",
			"location" : 
			{
				"x" : -63,
				"y" : 64,
				"z" : 10
			},
			"seller" : "NullCase",
			"time" : "2019/08/12",
			"type" : "buy",
			"volume" : 2600,
			"world" : "world"
		},
		{
			"amount" : 17,
			"buyer" : "ezrone",
			"location" : 
			{
				"x" : -63,
				"y" : 64,
				"z" : 10
			},
			"seller" : "NullCase",
			"time" : "2019/08/13",
			"type" : "buy",
			"volume" : 2210,
			"world" : "world"
		},
		{
			"amount" : 10,
			"buyer" : "ezrone",
			"location" : 
			{
				"x" : -63,
				"y" : 64,
				"z" : 10
			},
			"seller" : "NullCase",
			"time" : "2019/08/14",
			"type" : "buy",
			"volume" : 1300,
			"world" : "world"
		},
		{
			"amount" : 17,
			"buyer" : "AC391694",
			"location" : 
			{
				"x" : 363,
				"y" : 80,
				"z" : 187
			},
			"seller" : "Marcus265",
			"time" : "2019/08/17",
			"type" : "buy",
			"volume" : 1700,
			"world" : "world"
		},
		{
			"amount" : 4,
			"buyer" : "ezrone",
			"location" : 
			{
				"x" : -63,
				"y" : 64,
				"z" : 10
			},
			"seller" : "NullCase",
			"time" : "2019/08/18",
			"type" : "buy",
			"volume" : 520,
			"world" : "world"
		},
		{
			"amount" : 1,
			"buyer" : "Marcus265",
			"location" : 
			{
				"x" : -63,
				"y" : 64,
				"z" : 10
			},
			"seller" : "NullCase",
			"time" : "2019/08/18",
			"type" : "buy",
			"volume" : 130,
			"world" : "world"
		},
		{
			"amount" : 10,
			"buyer" : "ezrone",
			"location" : 
			{
				"x" : 276,
				"y" : 1,
				"z" : -207
			},
			"seller" : "Vallenius",
			"time" : "2019/08/19",
			"type" : "buy",
			"volume" : 60,
			"world" : "world_the_end"
		},
		{
			"amount" : 1,
			"buyer" : "TheNormalToast",
			"location" : 
			{
				"x" : 363,
				"y" : 80,
				"z" : 187
			},
			"seller" : "Marcus265",
			"time" : "2019/08/20",
			"type" : "buy",
			"volume" : 100,
			"world" : "world"
		},
		{
			"amount" : 173,
			"buyer" : "AC391694",
			"location" : 
			{
				"x" : 363,
				"y" : 80,
				"z" : 187
			},
			"seller" : "Marcus265",
			"time" : "2019/08/20",
			"type" : "buy",
			"volume" : 17300,
			"world" : "world"
		},
		{
			"amount" : 1,
			"buyer" : "NullCase",
			"location" : 
			{
				"x" : -63,
				"y" : 65,
				"z" : 10
			},
			"seller" : "PXshadow",
			"time" : "2019/08/20",
			"type" : "sell",
			"volume" : 75,
			"world" : "world"
		},
		{
			"amount" : 118,
			"buyer" : "NullCase",
			"location" : 
			{
				"x" : -63,
				"y" : 64,
				"z" : 10
			},
			"seller" : "PXshadow",
			"time" : "2019/08/20",
			"type" : "sell",
			"volume" : 12980,
			"world" : "world"
		},
		{
			"amount" : 119,
			"buyer" : "NullCase",
			"location" : 
			{
				"x" : -63,
				"y" : 65,
				"z" : 10
			},
			"seller" : "PXshadow",
			"time" : "2019/08/20",
			"type" : "sell",
			"volume" : 8925,
			"world" : "world"
		},
		{
			"amount" : 2,
			"buyer" : "Mathemagician4",
			"location" : 
			{
				"x" : -63,
				"y" : 65,
				"z" : 10
			},
			"seller" : "NullCase",
			"time" : "2019/08/30",
			"type" : "buy",
			"volume" : 158,
			"world" : "world"
		},
		{
			"amount" : 3,
			"buyer" : "Oaken_Ralph",
			"location" : 
			{
				"x" : -63,
				"y" : 65,
				"z" : 10
			},
			"seller" : "NullCase",
			"time" : "2019/08/31",
			"type" : "buy",
			"volume" : 237,
			"world" : "world"
		},
		{
			"amount" : 3,
			"buyer" : "johsjohsjohs",
			"location" : 
			{
				"x" : -63,
				"y" : 65,
				"z" : 10
			},
			"seller" : "NullCase",
			"time" : "2019/09/06",
			"type" : "buy",
			"volume" : 237,
			"world" : "world"
		},
		{
			"amount" : 10,
			"buyer" : "johsjohsjohs",
			"location" : 
			{
				"x" : -63,
				"y" : 65,
				"z" : 10
			},
			"seller" : "NullCase",
			"time" : "2019/09/07",
			"type" : "buy",
			"volume" : 790,
			"world" : "world"
		},
		{
			"amount" : 12,
			"buyer" : "Thoreu",
			"location" : 
			{
				"x" : 363,
				"y" : 80,
				"z" : 187
			},
			"seller" : "Marcus265",
			"time" : "2019/09/08",
			"type" : "buy",
			"volume" : 1200,
			"world" : "world"
		},
		{
			"amount" : 4,
			"buyer" : "johsjohsjohs",
			"location" : 
			{
				"x" : -63,
				"y" : 65,
				"z" : 10
			},
			"seller" : "NullCase",
			"time" : "2019/09/10",
			"type" : "buy",
			"volume" : 316,
			"world" : "world"
		},
		{
			"amount" : 36,
			"buyer" : "Downhilldriver",
			"location" : 
			{
				"x" : -63,
				"y" : 65,
				"z" : 10
			},
			"seller" : "NullCase",
			"time" : "2019/09/10",
			"type" : "buy",
			"volume" : 2844,
			"world" : "world"
		},
		{
			"amount" : 2,
			"buyer" : "johsjohsjohs",
			"location" : 
			{
				"x" : -63,
				"y" : 65,
				"z" : 10
			},
			"seller" : "NullCase",
			"time" : "2019/09/12",
			"type" : "buy",
			"volume" : 158,
			"world" : "world"
		},
		{
			"amount" : 9,
			"buyer" : "Thoreu",
			"location" : 
			{
				"x" : 363,
				"y" : 80,
				"z" : 187
			},
			"seller" : "Marcus265",
			"time" : "2019/09/12",
			"type" : "buy",
			"volume" : 900,
			"world" : "world"
		},
		{
			"amount" : 1,
			"buyer" : "vemppasalo",
			"location" : 
			{
				"x" : -63,
				"y" : 65,
				"z" : 10
			},
			"seller" : "NullCase",
			"time" : "2019/09/15",
			"type" : "buy",
			"volume" : 79,
			"world" : "world"
		},
		{
			"amount" : 2,
			"buyer" : "vemppasalo",
			"location" : 
			{
				"x" : -63,
				"y" : 63,
				"z" : 10
			},
			"seller" : "NullCase",
			"time" : "2019/09/15",
			"type" : "buy",
			"volume" : 390,
			"world" : "world"
		},
		{
			"amount" : 1,
			"buyer" : "Stormrunners",
			"location" : 
			{
				"x" : -333,
				"y" : 71,
				"z" : -476
			},
			"seller" : "EnDristON",
			"time" : "2019/09/17",
			"type" : "buy",
			"volume" : 120,
			"world" : "world"
		},
		{
			"amount" : 1,
			"buyer" : "vemppasalo",
			"location" : 
			{
				"x" : -63,
				"y" : 65,
				"z" : 10
			},
			"seller" : "NullCase",
			"time" : "2019/09/22",
			"type" : "buy",
			"volume" : 79,
			"world" : "world"
		},
		{
			"amount" : 1,
			"buyer" : "vemppasalo",
			"location" : 
			{
				"x" : -63,
				"y" : 63,
				"z" : 10
			},
			"seller" : "NullCase",
			"time" : "2019/09/22",
			"type" : "buy",
			"volume" : 195,
			"world" : "world"
		},
		{
			"amount" : 6,
			"buyer" : "vemppasalo",
			"location" : 
			{
				"x" : -63,
				"y" : 65,
				"z" : 10
			},
			"seller" : "NullCase",
			"time" : "2019/09/22",
			"type" : "buy",
			"volume" : 474,
			"world" : "world"
		},
		{
			"amount" : 3,
			"buyer" : "AshGreninja2579",
			"location" : 
			{
				"x" : -63,
				"y" : 63,
				"z" : 10
			},
			"seller" : "NullCase",
			"time" : "2019/10/14",
			"type" : "buy",
			"volume" : 585,
			"world" : "world"
		},
		{
			"amount" : 2,
			"buyer" : "NullCase",
			"location" : 
			{
				"x" : -63,
				"y" : 63,
				"z" : 10
			},
			"seller" : "AshGreninja2579",
			"time" : "2019/10/14",
			"type" : "sell",
			"volume" : 354,
			"world" : "world"
		},
		{
			"amount" : 24,
			"buyer" : "AshGreninja2579",
			"location" : 
			{
				"x" : -63,
				"y" : 63,
				"z" : 10
			},
			"seller" : "NullCase",
			"time" : "2019/10/23",
			"type" : "buy",
			"volume" : 4680,
			"world" : "world"
		},
		{
			"amount" : 8,
			"buyer" : "NullCase",
			"location" : 
			{
				"x" : -63,
				"y" : 65,
				"z" : 10
			},
			"seller" : "illdeletethis",
			"time" : "2019/10/30",
			"type" : "sell",
			"volume" : 600,
			"world" : "world"
		},
		{
			"amount" : 16,
			"buyer" : "NullCase",
			"location" : 
			{
				"x" : -63,
				"y" : 63,
				"z" : 10
			},
			"seller" : "illdeletethis",
			"time" : "2019/10/30",
			"type" : "sell",
			"volume" : 2832,
			"world" : "world"
		},
		{
			"amount" : 17,
			"buyer" : "illdeletethis",
			"location" : 
			{
				"x" : -63,
				"y" : 63,
				"z" : 10
			},
			"seller" : "NullCase",
			"time" : "2019/10/30",
			"type" : "buy",
			"volume" : 3315,
			"world" : "world"
		},
		{
			"amount" : 29,
			"buyer" : "NullCase",
			"location" : 
			{
				"x" : -63,
				"y" : 63,
				"z" : 10
			},
			"seller" : "illdeletethis",
			"time" : "2019/10/30",
			"type" : "sell",
			"volume" : 5133,
			"world" : "world"
		},
		{
			"amount" : 28,
			"buyer" : "NullCase",
			"location" : 
			{
				"x" : -63,
				"y" : 65,
				"z" : 10
			},
			"seller" : "illdeletethis",
			"time" : "2019/10/30",
			"type" : "sell",
			"volume" : 2100,
			"world" : "world"
		},
		{
			"amount" : 26,
			"buyer" : "ZeroGDucks",
			"location" : 
			{
				"x" : 55,
				"y" : 88,
				"z" : 15
			},
			"seller" : "Remix_D_Miner",
			"time" : "2019/11/14",
			"type" : "buy",
			"volume" : 1300,
			"world" : "world"
		},
		{
			"amount" : 1,
			"buyer" : "ZeroGDucks",
			"location" : 
			{
				"x" : -63,
				"y" : 63,
				"z" : 10
			},
			"seller" : "NullCase",
			"time" : "2019/11/14",
			"type" : "buy",
			"volume" : 195,
			"world" : "world"
		},
		{
			"amount" : 1,
			"buyer" : "NullCase",
			"location" : 
			{
				"x" : -63,
				"y" : 63,
				"z" : 10
			},
			"seller" : "ZeroGDucks",
			"time" : "2019/11/14",
			"type" : "sell",
			"volume" : 177,
			"world" : "world"
		},
		{
			"amount" : 2,
			"buyer" : "NullCase",
			"location" : 
			{
				"x" : -63,
				"y" : 65,
				"z" : 10
			},
			"seller" : "ZeroGDucks",
			"time" : "2019/11/14",
			"type" : "sell",
			"volume" : 150,
			"world" : "world"
		},
		{
			"amount" : 41,
			"buyer" : "ZeroGDucks",
			"location" : 
			{
				"x" : 55,
				"y" : 88,
				"z" : 15
			},
			"seller" : "Remix_D_Miner",
			"time" : "2019/11/15",
			"type" : "buy",
			"volume" : 2050,
			"world" : "world"
		},
		{
			"amount" : 1,
			"buyer" : "mendor77",
			"location" : 
			{
				"x" : -63,
				"y" : 64,
				"z" : 10
			},
			"seller" : "NullCase",
			"time" : "2019/11/15",
			"type" : "buy",
			"volume" : 130,
			"world" : "world"
		},
		{
			"amount" : 1,
			"buyer" : "NullCase",
			"location" : 
			{
				"x" : -63,
				"y" : 64,
				"z" : 10
			},
			"seller" : "mendor77",
			"time" : "2019/11/15",
			"type" : "sell",
			"volume" : 110,
			"world" : "world"
		},
		{
			"amount" : 1,
			"buyer" : "mendor77",
			"location" : 
			{
				"x" : -63,
				"y" : 63,
				"z" : 10
			},
			"seller" : "NullCase",
			"time" : "2019/11/15",
			"type" : "buy",
			"volume" : 195,
			"world" : "world"
		},
		{
			"amount" : 1,
			"buyer" : "NullCase",
			"location" : 
			{
				"x" : -63,
				"y" : 63,
				"z" : 10
			},
			"seller" : "mendor77",
			"time" : "2019/11/15",
			"type" : "sell",
			"volume" : 177,
			"world" : "world"
		},
		{
			"amount" : 1,
			"buyer" : "mendor77",
			"location" : 
			{
				"x" : -63,
				"y" : 63,
				"z" : 10
			},
			"seller" : "NullCase",
			"time" : "2019/11/16",
			"type" : "buy",
			"volume" : 195,
			"world" : "world"
		},
		{
			"amount" : 1,
			"buyer" : "NullCase",
			"location" : 
			{
				"x" : -63,
				"y" : 63,
				"z" : 10
			},
			"seller" : "mendor77",
			"time" : "2019/11/16",
			"type" : "sell",
			"volume" : 177,
			"world" : "world"
		},
		{
			"amount" : 53,
			"buyer" : "Vallenius",
			"location" : 
			{
				"x" : -63,
				"y" : 65,
				"z" : 10
			},
			"seller" : "NullCase",
			"time" : "2019/11/30",
			"type" : "buy",
			"volume" : 4187,
			"world" : "world"
		},
		{
			"amount" : 64,
			"buyer" : "Vallenius",
			"location" : 
			{
				"x" : -63,
				"y" : 64,
				"z" : 10
			},
			"seller" : "NullCase",
			"time" : "2019/11/30",
			"type" : "buy",
			"volume" : 8320,
			"world" : "world"
		},
		{
			"amount" : 64,
			"buyer" : "Vallenius",
			"location" : 
			{
				"x" : -63,
				"y" : 64,
				"z" : 10
			},
			"seller" : "NullCase",
			"time" : "2019/12/05",
			"type" : "buy",
			"volume" : 8320,
			"world" : "world"
		},
		{
			"amount" : 128,
			"buyer" : "NullCase",
			"location" : 
			{
				"x" : -63,
				"y" : 64,
				"z" : 10
			},
			"seller" : "illdeletethis",
			"time" : "2019/12/10",
			"type" : "sell",
			"volume" : 14080,
			"world" : "world"
		},
		{
			"amount" : 446,
			"buyer" : "NullCase",
			"location" : 
			{
				"x" : -63,
				"y" : 65,
				"z" : 10
			},
			"seller" : "illdeletethis",
			"time" : "2019/12/10",
			"type" : "sell",
			"volume" : 33450,
			"world" : "world"
		},
		{
			"amount" : 128,
			"buyer" : "Vallenius",
			"location" : 
			{
				"x" : -63,
				"y" : 65,
				"z" : 10
			},
			"seller" : "NullCase",
			"time" : "2019/12/15",
			"type" : "buy",
			"volume" : 10112,
			"world" : "world"
		},
		{
			"amount" : 23,
			"buyer" : "NullCase",
			"location" : 
			{
				"x" : -63,
				"y" : 65,
				"z" : 10
			},
			"seller" : "illdeletethis",
			"time" : "2019/12/22",
			"type" : "sell",
			"volume" : 1725,
			"world" : "world"
		},
		{
			"amount" : 203,
			"buyer" : "NullCase",
			"location" : 
			{
				"x" : -63,
				"y" : 65,
				"z" : 10
			},
			"seller" : "illdeletethis",
			"time" : "2019/12/23",
			"type" : "sell",
			"volume" : 15225,
			"world" : "world"
		},
		{
			"amount" : 3,
			"buyer" : "RyanJG",
			"location" : 
			{
				"x" : -63,
				"y" : 65,
				"z" : 10
			},
			"seller" : "NullCase",
			"time" : "2019/12/27",
			"type" : "buy",
			"volume" : 237,
			"world" : "world"
		},
		{
			"amount" : 65,
			"buyer" : "jtl0350",
			"location" : 
			{
				"x" : -63,
				"y" : 65,
				"z" : 10
			},
			"seller" : "NullCase",
			"time" : "2020/01/10",
			"type" : "buy",
			"volume" : 5135,
			"world" : "world"
		},
		{
			"amount" : 1,
			"buyer" : "jtl0350",
			"location" : 
			{
				"x" : -63,
				"y" : 63,
				"z" : 10
			},
			"seller" : "NullCase",
			"time" : "2020/01/10",
			"type" : "buy",
			"volume" : 195,
			"world" : "world"
		},
		{
			"amount" : 1,
			"buyer" : "NullCase",
			"location" : 
			{
				"x" : -63,
				"y" : 63,
				"z" : 10
			},
			"seller" : "jtl0350",
			"time" : "2020/01/10",
			"type" : "sell",
			"volume" : 177,
			"world" : "world"
		},
		{
			"amount" : 5,
			"buyer" : "NullCase",
			"location" : 
			{
				"x" : -63,
				"y" : 65,
				"z" : 10
			},
			"seller" : "jtl0350",
			"time" : "2020/01/10",
			"type" : "sell",
			"volume" : 375,
			"world" : "world"
		},
		{
			"amount" : 1,
			"buyer" : "jtl0350",
			"location" : 
			{
				"x" : -63,
				"y" : 65,
				"z" : 10
			},
			"seller" : "NullCase",
			"time" : "2020/01/10",
			"type" : "buy",
			"volume" : 79,
			"world" : "world"
		},
		{
			"amount" : 4,
			"buyer" : "jtl0350",
			"location" : 
			{
				"x" : -63,
				"y" : 65,
				"z" : 10
			},
			"seller" : "NullCase",
			"time" : "2020/01/13",
			"type" : "buy",
			"volume" : 316,
			"world" : "world"
		},
		{
			"amount" : 7,
			"buyer" : "Tomter",
			"location" : 
			{
				"x" : -333,
				"y" : 71,
				"z" : -476
			},
			"seller" : "EnDristON",
			"time" : "2020/01/13",
			"type" : "buy",
			"volume" : 840,
			"world" : "world"
		},
		{
			"amount" : 4,
			"buyer" : "AmineWeboo",
			"location" : 
			{
				"x" : -63,
				"y" : 65,
				"z" : 10
			},
			"seller" : "NullCase",
			"time" : "2020/01/15",
			"type" : "buy",
			"volume" : 316,
			"world" : "world"
		},
		{
			"amount" : 1,
			"buyer" : "AmineWeboo",
			"location" : 
			{
				"x" : -63,
				"y" : 65,
				"z" : 10
			},
			"seller" : "NullCase",
			"time" : "2020/01/18",
			"type" : "buy",
			"volume" : 79,
			"world" : "world"
		},
		{
			"amount" : 2,
			"buyer" : "Freeaboo",
			"location" : 
			{
				"x" : -63,
				"y" : 65,
				"z" : 10
			},
			"seller" : "NullCase",
			"time" : "2020/01/18",
			"type" : "buy",
			"volume" : 158,
			"world" : "world"
		},
		{
			"amount" : 1,
			"buyer" : "AmineWeboo",
			"location" : 
			{
				"x" : -63,
				"y" : 65,
				"z" : 10
			},
			"seller" : "NullCase",
			"time" : "2020/01/20",
			"type" : "buy",
			"volume" : 79,
			"world" : "world"
		},
		{
			"amount" : 1,
			"buyer" : "Freeaboo",
			"location" : 
			{
				"x" : -63,
				"y" : 65,
				"z" : 10
			},
			"seller" : "NullCase",
			"time" : "2020/01/20",
			"type" : "buy",
			"volume" : 79,
			"world" : "world"
		},
		{
			"amount" : 1,
			"buyer" : "Skypoison",
			"location" : 
			{
				"x" : -63,
				"y" : 65,
				"z" : 10
			},
			"seller" : "NullCase",
			"time" : "2020/01/20",
			"type" : "buy",
			"volume" : 79,
			"world" : "world"
		},
		{
			"amount" : 129,
			"buyer" : "NullCase",
			"location" : 
			{
				"x" : -63,
				"y" : 65,
				"z" : 10
			},
			"seller" : "Skypoison",
			"time" : "2020/01/20",
			"type" : "sell",
			"volume" : 9675,
			"world" : "world"
		},
		{
			"amount" : 73,
			"buyer" : "Freeaboo",
			"location" : 
			{
				"x" : -63,
				"y" : 65,
				"z" : 10
			},
			"seller" : "NullCase",
			"time" : "2020/01/20",
			"type" : "buy",
			"volume" : 5767,
			"world" : "world"
		},
		{
			"amount" : 266,
			"buyer" : "NullCase",
			"location" : 
			{
				"x" : -63,
				"y" : 65,
				"z" : 10
			},
			"seller" : "Freeaboo",
			"time" : "2020/01/20",
			"type" : "sell",
			"volume" : 19950,
			"world" : "world"
		},
		{
			"amount" : 1,
			"buyer" : "NullCase",
			"location" : 
			{
				"x" : -63,
				"y" : 65,
				"z" : 10
			},
			"seller" : "_mrpuggy_",
			"time" : "2020/01/28",
			"type" : "sell",
			"volume" : 75,
			"world" : "world"
		},
		{
			"amount" : 41,
			"buyer" : "_mrpuggy_",
			"location" : 
			{
				"x" : -63,
				"y" : 65,
				"z" : 10
			},
			"seller" : "NullCase",
			"time" : "2020/01/28",
			"type" : "buy",
			"volume" : 3239,
			"world" : "world"
		},
		{
			"amount" : 47,
			"buyer" : "NullCase",
			"location" : 
			{
				"x" : -63,
				"y" : 65,
				"z" : 10
			},
			"seller" : "_mrpuggy_",
			"time" : "2020/01/28",
			"type" : "sell",
			"volume" : 3525,
			"world" : "world"
		},
		{
			"amount" : 7,
			"buyer" : "_mrpuggy_",
			"location" : 
			{
				"x" : -63,
				"y" : 65,
				"z" : 10
			},
			"seller" : "NullCase",
			"time" : "2020/01/28",
			"type" : "buy",
			"volume" : 553,
			"world" : "world"
		},
		{
			"amount" : 1,
			"buyer" : "_mrpuggy_",
			"location" : 
			{
				"x" : -63,
				"y" : 64,
				"z" : 10
			},
			"seller" : "NullCase",
			"time" : "2020/01/28",
			"type" : "buy",
			"volume" : 130,
			"world" : "world"
		},
		{
			"amount" : 4,
			"buyer" : "_mrpuggy_",
			"location" : 
			{
				"x" : -63,
				"y" : 65,
				"z" : 10
			},
			"seller" : "NullCase",
			"time" : "2020/01/29",
			"type" : "buy",
			"volume" : 316,
			"world" : "world"
		},
		{
			"amount" : 14,
			"buyer" : "Miiirak",
			"location" : 
			{
				"x" : -63,
				"y" : 65,
				"z" : 10
			},
			"seller" : "NullCase",
			"time" : "2020/01/29",
			"type" : "buy",
			"volume" : 1106,
			"world" : "world"
		},
		{
			"amount" : 64,
			"buyer" : "Thoreu",
			"location" : 
			{
				"x" : 276,
				"y" : 1,
				"z" : -207
			},
			"seller" : "Vallenius",
			"time" : "2020/02/05",
			"type" : "buy",
			"volume" : 384,
			"world" : "world_the_end"
		},
		{
			"amount" : 8,
			"buyer" : "Pancen",
			"location" : 
			{
				"x" : -63,
				"y" : 65,
				"z" : 10
			},
			"seller" : "NullCase",
			"time" : "2020/02/15",
			"type" : "buy",
			"volume" : 632,
			"world" : "world"
		},
		{
			"amount" : 1,
			"buyer" : "NullCase",
			"location" : 
			{
				"x" : -63,
				"y" : 65,
				"z" : 10
			},
			"seller" : "exrook",
			"time" : "2020/02/15",
			"type" : "sell",
			"volume" : 75,
			"world" : "world"
		},
		{
			"amount" : 1,
			"buyer" : "NullCase",
			"location" : 
			{
				"x" : -63,
				"y" : 64,
				"z" : 10
			},
			"seller" : "exrook",
			"time" : "2020/02/15",
			"type" : "sell",
			"volume" : 110,
			"world" : "world"
		},
		{
			"amount" : 3,
			"buyer" : "NullCase",
			"location" : 
			{
				"x" : -63,
				"y" : 65,
				"z" : 10
			},
			"seller" : "exrook",
			"time" : "2020/02/15",
			"type" : "sell",
			"volume" : 225,
			"world" : "world"
		},
		{
			"amount" : 7,
			"buyer" : "Vallenius",
			"location" : 
			{
				"x" : -63,
				"y" : 65,
				"z" : 10
			},
			"seller" : "NullCase",
			"time" : "2020/02/17",
			"type" : "buy",
			"volume" : 553,
			"world" : "world"
		},
		{
			"amount" : 6,
			"buyer" : "Minarchu",
			"location" : 
			{
				"x" : -63,
				"y" : 65,
				"z" : 10
			},
			"seller" : "NullCase",
			"time" : "2020/02/25",
			"type" : "buy",
			"volume" : 474,
			"world" : "world"
		},
		{
			"amount" : 1,
			"buyer" : "Miss_Animator",
			"location" : 
			{
				"x" : -63,
				"y" : 65,
				"z" : 10
			},
			"seller" : "NullCase",
			"time" : "2020/02/26",
			"type" : "buy",
			"volume" : 79,
			"world" : "world"
		},
		{
			"amount" : 1,
			"buyer" : "Miss_Animator",
			"location" : 
			{
				"x" : -63,
				"y" : 63,
				"z" : 10
			},
			"seller" : "NullCase",
			"time" : "2020/02/27",
			"type" : "buy",
			"volume" : 195,
			"world" : "world"
		},
		{
			"amount" : 3,
			"buyer" : "Minarchu",
			"location" : 
			{
				"x" : -63,
				"y" : 65,
				"z" : 10
			},
			"seller" : "NullCase",
			"time" : "2020/02/29",
			"type" : "buy",
			"volume" : 237,
			"world" : "world"
		},
		{
			"amount" : 3,
			"buyer" : "NullCase",
			"location" : 
			{
				"x" : -63,
				"y" : 65,
				"z" : 10
			},
			"seller" : "Minarchu",
			"time" : "2020/02/29",
			"type" : "sell",
			"volume" : 225,
			"world" : "world"
		},
		{
			"amount" : 45,
			"buyer" : "Qu1dz0",
			"location" : 
			{
				"x" : -63,
				"y" : 65,
				"z" : 10
			},
			"seller" : "NullCase",
			"time" : "2020/03/01",
			"type" : "buy",
			"volume" : 3555,
			"world" : "world"
		},
		{
			"amount" : 64,
			"buyer" : "TheMotherBrayne",
			"location" : 
			{
				"x" : 55,
				"y" : 88,
				"z" : 15
			},
			"seller" : "Remix_D_Miner",
			"time" : "2020/03/01",
			"type" : "buy",
			"volume" : 3200,
			"world" : "world"
		},
		{
			"amount" : 63,
			"buyer" : "TheMotherBrayne",
			"location" : 
			{
				"x" : -63,
				"y" : 65,
				"z" : 10
			},
			"seller" : "NullCase",
			"time" : "2020/03/02",
			"type" : "buy",
			"volume" : 4977,
			"world" : "world"
		},
		{
			"amount" : 8,
			"buyer" : "VeillofSorrow",
			"location" : 
			{
				"x" : 55,
				"y" : 88,
				"z" : 15
			},
			"seller" : "Remix_D_Miner",
			"time" : "2020/03/02",
			"type" : "buy",
			"volume" : 400,
			"world" : "world"
		},
		{
			"amount" : 144,
			"buyer" : "TheMotherBrayne",
			"location" : 
			{
				"x" : -63,
				"y" : 65,
				"z" : 10
			},
			"seller" : "NullCase",
			"time" : "2020/03/02",
			"type" : "buy",
			"volume" : 11376,
			"world" : "world"
		},
		{
			"amount" : 1,
			"buyer" : "Vallenius",
			"location" : 
			{
				"x" : -63,
				"y" : 64,
				"z" : 10
			},
			"seller" : "NullCase",
			"time" : "2020/03/03",
			"type" : "buy",
			"volume" : 130,
			"world" : "world"
		},
		{
			"amount" : 10,
			"buyer" : "Vallenius",
			"location" : 
			{
				"x" : -63,
				"y" : 65,
				"z" : 10
			},
			"seller" : "NullCase",
			"time" : "2020/03/03",
			"type" : "buy",
			"volume" : 790,
			"world" : "world"
		},
		{
			"amount" : 8,
			"buyer" : "Vallenius",
			"location" : 
			{
				"x" : -63,
				"y" : 65,
				"z" : 10
			},
			"seller" : "NullCase",
			"time" : "2020/03/05",
			"type" : "buy",
			"volume" : 632,
			"world" : "world"
		},
		{
			"amount" : 1,
			"buyer" : "NullCase",
			"location" : 
			{
				"x" : -63,
				"y" : 64,
				"z" : 10
			},
			"seller" : "Minarchu",
			"time" : "2020/03/07",
			"type" : "sell",
			"volume" : 110,
			"world" : "world"
		},
		{
			"amount" : 1,
			"buyer" : "NullCase",
			"location" : 
			{
				"x" : -63,
				"y" : 63,
				"z" : 10
			},
			"seller" : "Minarchu",
			"time" : "2020/03/07",
			"type" : "sell",
			"volume" : 177,
			"world" : "world"
		},
		{
			"amount" : 12,
			"buyer" : "NullCase",
			"location" : 
			{
				"x" : -63,
				"y" : 65,
				"z" : 10
			},
			"seller" : "Minarchu",
			"time" : "2020/03/07",
			"type" : "sell",
			"volume" : 900,
			"world" : "world"
		},
		{
			"amount" : 4,
			"buyer" : "TheMotherBrayne",
			"location" : 
			{
				"x" : -63,
				"y" : 65,
				"z" : 10
			},
			"seller" : "NullCase",
			"time" : "2020/03/07",
			"type" : "buy",
			"volume" : 316,
			"world" : "world"
		},
		{
			"amount" : 1,
			"buyer" : "solson744",
			"location" : 
			{
				"x" : -63,
				"y" : 65,
				"z" : 10
			},
			"seller" : "NullCase",
			"time" : "2020/03/08",
			"type" : "buy",
			"volume" : 79,
			"world" : "world"
		},
		{
			"amount" : 1,
			"buyer" : "YeetSauceLicker",
			"location" : 
			{
				"x" : -63,
				"y" : 65,
				"z" : 10
			},
			"seller" : "NullCase",
			"time" : "2020/03/08",
			"type" : "buy",
			"volume" : 79,
			"world" : "world"
		},
		{
			"amount" : 1,
			"buyer" : "NullCase",
			"location" : 
			{
				"x" : -63,
				"y" : 65,
				"z" : 10
			},
			"seller" : "YeetSauceLicker",
			"time" : "2020/03/08",
			"type" : "sell",
			"volume" : 75,
			"world" : "world"
		},
		{
			"amount" : 1,
			"buyer" : "VeillofSorrow",
			"location" : 
			{
				"x" : -63,
				"y" : 65,
				"z" : 10
			},
			"seller" : "NullCase",
			"time" : "2020/03/09",
			"type" : "buy",
			"volume" : 79,
			"world" : "world"
		},
		{
			"amount" : 2,
			"buyer" : "Minarchu",
			"location" : 
			{
				"x" : -63,
				"y" : 65,
				"z" : 10
			},
			"seller" : "NullCase",
			"time" : "2020/03/10",
			"type" : "buy",
			"volume" : 158,
			"world" : "world"
		},
		{
			"amount" : 1,
			"buyer" : "hyperdramallama",
			"location" : 
			{
				"x" : -63,
				"y" : 65,
				"z" : 10
			},
			"seller" : "NullCase",
			"time" : "2020/03/12",
			"type" : "buy",
			"volume" : 79,
			"world" : "world"
		},
		{
			"amount" : 1,
			"buyer" : "hyperdramallama",
			"location" : 
			{
				"x" : -63,
				"y" : 64,
				"z" : 10
			},
			"seller" : "NullCase",
			"time" : "2020/03/12",
			"type" : "buy",
			"volume" : 130,
			"world" : "world"
		},
		{
			"amount" : 5,
			"buyer" : "hyperdramallama",
			"location" : 
			{
				"x" : -63,
				"y" : 65,
				"z" : 10
			},
			"seller" : "NullCase",
			"time" : "2020/03/12",
			"type" : "buy",
			"volume" : 395,
			"world" : "world"
		},
		{
			"amount" : 1,
			"buyer" : "hyperdramallama",
			"location" : 
			{
				"x" : -63,
				"y" : 64,
				"z" : 10
			},
			"seller" : "NullCase",
			"time" : "2020/03/16",
			"type" : "buy",
			"volume" : 130,
			"world" : "world"
		},
		{
			"amount" : 1,
			"buyer" : "TheMotherBrayne",
			"location" : 
			{
				"x" : -63,
				"y" : 64,
				"z" : 10
			},
			"seller" : "NullCase",
			"time" : "2020/03/19",
			"type" : "buy",
			"volume" : 130,
			"world" : "world"
		},
		{
			"amount" : 35,
			"buyer" : "NullCase",
			"location" : 
			{
				"x" : -63,
				"y" : 64,
				"z" : 10
			},
			"seller" : "Shadows_Strike",
			"time" : "2020/03/19",
			"type" : "sell",
			"volume" : 3850,
			"world" : "world"
		},
		{
			"amount" : 29,
			"buyer" : "NullCase",
			"location" : 
			{
				"x" : -63,
				"y" : 65,
				"z" : 10
			},
			"seller" : "Shadows_Strike",
			"time" : "2020/03/19",
			"type" : "sell",
			"volume" : 2175,
			"world" : "world"
		},
		{
			"amount" : 6,
			"buyer" : "TheMotherBrayne",
			"location" : 
			{
				"x" : -63,
				"y" : 65,
				"z" : 10
			},
			"seller" : "NullCase",
			"time" : "2020/03/22",
			"type" : "buy",
			"volume" : 474,
			"world" : "world"
		},
		{
			"amount" : 2,
			"buyer" : "NullCase",
			"location" : 
			{
				"x" : -63,
				"y" : 65,
				"z" : 10
			},
			"seller" : "Minarchu",
			"time" : "2020/03/24",
			"type" : "sell",
			"volume" : 150,
			"world" : "world"
		},
		{
			"amount" : 5,
			"buyer" : "KnobbyWaffle",
			"location" : 
			{
				"x" : -63,
				"y" : 65,
				"z" : 10
			},
			"seller" : "NullCase",
			"time" : "2020/03/26",
			"type" : "buy",
			"volume" : 395,
			"world" : "world"
		},
		{
			"amount" : 1,
			"buyer" : "Greenbarn1234",
			"location" : 
			{
				"x" : -63,
				"y" : 65,
				"z" : 10
			},
			"seller" : "NullCase",
			"time" : "2020/03/26",
			"type" : "buy",
			"volume" : 79,
			"world" : "world"
		},
		{
			"amount" : 11,
			"buyer" : "KnobbyWaffle",
			"location" : 
			{
				"x" : -63,
				"y" : 65,
				"z" : 10
			},
			"seller" : "NullCase",
			"time" : "2020/03/26",
			"type" : "buy",
			"volume" : 869,
			"world" : "world"
		},
		{
			"amount" : 7,
			"buyer" : "KnobbyWaffle",
			"location" : 
			{
				"x" : -63,
				"y" : 65,
				"z" : 10
			},
			"seller" : "NullCase",
			"time" : "2020/03/27",
			"type" : "buy",
			"volume" : 553,
			"world" : "world"
		},
		{
			"amount" : 1,
			"buyer" : "miniman927",
			"location" : 
			{
				"x" : -63,
				"y" : 65,
				"z" : 10
			},
			"seller" : "NullCase",
			"time" : "2020/03/27",
			"type" : "buy",
			"volume" : 79,
			"world" : "world"
		},
		{
			"amount" : 19,
			"buyer" : "miniman927",
			"location" : 
			{
				"x" : -63,
				"y" : 64,
				"z" : 10
			},
			"seller" : "NullCase",
			"time" : "2020/03/27",
			"type" : "buy",
			"volume" : 2470,
			"world" : "world"
		}
	]
}