{
	"item name" : "Clay",
	"transactions" : 
	[
		{
			"amount" : 23,
			"buyer" : "K9us",
			"location" : 
			{
				"x" : 35,
				"y" : 71,
				"z" : -24
			},
			"seller" : "mendor77",
			"time" : "2019/02/09",
			"type" : "sell",
			"volume" : 575,
			"world" : "world"
		},
		{
			"amount" : 128,
			"buyer" : "Vallenius",
			"location" : 
			{
				"x" : 35,
				"y" : 71,
				"z" : -24
			},
			"seller" : "K9us",
			"time" : "2019/02/28",
			"type" : "buy",
			"volume" : 6400,
			"world" : "world"
		}
	]
}