{
	"item name" : "Diamond Helmet#1S",
	"transactions" : 
	[
		{
			"amount" : 1,
			"buyer" : "Rehns",
			"location" : 
			{
				"x" : 40,
				"y" : 82,
				"z" : -14
			},
			"seller" : "K9us",
			"time" : "2018/09/28",
			"type" : "buy",
			"volume" : 200000,
			"world" : "world"
		},
		{
			"amount" : 1,
			"buyer" : "Haksndot",
			"location" : 
			{
				"x" : 40,
				"y" : 82,
				"z" : -14
			},
			"seller" : "K9us",
			"time" : "2018/09/30",
			"type" : "buy",
			"volume" : 220000,
			"world" : "world"
		},
		{
			"amount" : 1,
			"buyer" : "Baskerboss",
			"location" : 
			{
				"x" : 40,
				"y" : 82,
				"z" : -14
			},
			"seller" : "K9us",
			"time" : "2018/10/06",
			"type" : "buy",
			"volume" : 240000,
			"world" : "world"
		}
	]
}