{
	"item name" : "Diamond Pickaxe#3i",
	"transactions" : 
	[
		{
			"amount" : 4,
			"buyer" : "K9us",
			"location" : 
			{
				"x" : -9,
				"y" : 68,
				"z" : 18
			},
			"seller" : "sharonclaws",
			"time" : "2018/10/24",
			"type" : "buy",
			"volume" : 40000,
			"world" : "world"
		},
		{
			"amount" : 2,
			"buyer" : "Haksndot",
			"location" : 
			{
				"x" : -9,
				"y" : 68,
				"z" : 18
			},
			"seller" : "sharonclaws",
			"time" : "2018/10/28",
			"type" : "buy",
			"volume" : 20000,
			"world" : "world"
		},
		{
			"amount" : 1,
			"buyer" : "daggvad",
			"location" : 
			{
				"x" : -9,
				"y" : 68,
				"z" : 18
			},
			"seller" : "sharonclaws",
			"time" : "2018/10/29",
			"type" : "buy",
			"volume" : 10000,
			"world" : "world"
		},
		{
			"amount" : 1,
			"buyer" : "Aewheros",
			"location" : 
			{
				"x" : -9,
				"y" : 68,
				"z" : 18
			},
			"seller" : "sharonclaws",
			"time" : "2018/10/29",
			"type" : "buy",
			"volume" : 10000,
			"world" : "world"
		},
		{
			"amount" : 9,
			"buyer" : "K9us",
			"location" : 
			{
				"x" : -9,
				"y" : 68,
				"z" : 18
			},
			"seller" : "sharonclaws",
			"time" : "2018/11/02",
			"type" : "buy",
			"volume" : 90000,
			"world" : "world"
		},
		{
			"amount" : 1,
			"buyer" : "pudzo",
			"location" : 
			{
				"x" : -9,
				"y" : 68,
				"z" : 18
			},
			"seller" : "sharonclaws",
			"time" : "2018/11/04",
			"type" : "buy",
			"volume" : 10000,
			"world" : "world"
		},
		{
			"amount" : 1,
			"buyer" : "pudzo",
			"location" : 
			{
				"x" : -9,
				"y" : 68,
				"z" : 18
			},
			"seller" : "sharonclaws",
			"time" : "2018/11/06",
			"type" : "buy",
			"volume" : 10000,
			"world" : "world"
		},
		{
			"amount" : 1,
			"buyer" : "Engineerer",
			"location" : 
			{
				"x" : -9,
				"y" : 68,
				"z" : 18
			},
			"seller" : "sharonclaws",
			"time" : "2018/11/06",
			"type" : "buy",
			"volume" : 10000,
			"world" : "world"
		},
		{
			"amount" : 1,
			"buyer" : "Shahayhay",
			"location" : 
			{
				"x" : -9,
				"y" : 68,
				"z" : 18
			},
			"seller" : "sharonclaws",
			"time" : "2018/11/12",
			"type" : "buy",
			"volume" : 10000,
			"world" : "world"
		},
		{
			"amount" : 1,
			"buyer" : "Rille3000",
			"location" : 
			{
				"x" : -9,
				"y" : 68,
				"z" : 18
			},
			"seller" : "sharonclaws",
			"time" : "2018/11/15",
			"type" : "buy",
			"volume" : 10000,
			"world" : "world"
		},
		{
			"amount" : 1,
			"buyer" : "Aewheros",
			"location" : 
			{
				"x" : -9,
				"y" : 68,
				"z" : 18
			},
			"seller" : "sharonclaws",
			"time" : "2018/11/18",
			"type" : "buy",
			"volume" : 10000,
			"world" : "world"
		},
		{
			"amount" : 1,
			"buyer" : "AteUrC00ki35",
			"location" : 
			{
				"x" : -9,
				"y" : 68,
				"z" : 18
			},
			"seller" : "sharonclaws",
			"time" : "2018/12/04",
			"type" : "buy",
			"volume" : 10000,
			"world" : "world"
		},
		{
			"amount" : 1,
			"buyer" : "MemeKingAwesome",
			"location" : 
			{
				"x" : -9,
				"y" : 68,
				"z" : 18
			},
			"seller" : "sharonclaws",
			"time" : "2018/12/09",
			"type" : "buy",
			"volume" : 5000,
			"world" : "world"
		},
		{
			"amount" : 1,
			"buyer" : "TheScrubJay",
			"location" : 
			{
				"x" : -9,
				"y" : 68,
				"z" : 18
			},
			"seller" : "sharonclaws",
			"time" : "2018/12/24",
			"type" : "buy",
			"volume" : 5000,
			"world" : "world"
		},
		{
			"amount" : 1,
			"buyer" : "Trixemfixem",
			"location" : 
			{
				"x" : -106,
				"y" : 65,
				"z" : -4
			},
			"seller" : "K9us",
			"time" : "2019/01/19",
			"type" : "buy",
			"volume" : 2500,
			"world" : "world"
		},
		{
			"amount" : 1,
			"buyer" : "Zarigan0",
			"location" : 
			{
				"x" : -106,
				"y" : 65,
				"z" : -4
			},
			"seller" : "K9us",
			"time" : "2019/01/24",
			"type" : "buy",
			"volume" : 2500,
			"world" : "world"
		},
		{
			"amount" : 1,
			"buyer" : "Nocturna12",
			"location" : 
			{
				"x" : -106,
				"y" : 65,
				"z" : -4
			},
			"seller" : "K9us",
			"time" : "2019/01/28",
			"type" : "buy",
			"volume" : 2500,
			"world" : "world"
		},
		{
			"amount" : 1,
			"buyer" : "P1st0n",
			"location" : 
			{
				"x" : -9,
				"y" : 68,
				"z" : 18
			},
			"seller" : "sharonclaws",
			"time" : "2019/01/31",
			"type" : "buy",
			"volume" : 2000,
			"world" : "world"
		},
		{
			"amount" : 1,
			"buyer" : "magemagemege",
			"location" : 
			{
				"x" : -106,
				"y" : 65,
				"z" : -4
			},
			"seller" : "K9us",
			"time" : "2019/02/04",
			"type" : "buy",
			"volume" : 2500,
			"world" : "world"
		},
		{
			"amount" : 1,
			"buyer" : "monkeyboy448",
			"location" : 
			{
				"x" : -9,
				"y" : 68,
				"z" : 18
			},
			"seller" : "sharonclaws",
			"time" : "2019/02/06",
			"type" : "buy",
			"volume" : 2000,
			"world" : "world"
		},
		{
			"amount" : 1,
			"buyer" : "freakdown",
			"location" : 
			{
				"x" : -9,
				"y" : 68,
				"z" : 18
			},
			"seller" : "sharonclaws",
			"time" : "2019/02/11",
			"type" : "buy",
			"volume" : 2000,
			"world" : "world"
		},
		{
			"amount" : 1,
			"buyer" : "EnDristON",
			"location" : 
			{
				"x" : -106,
				"y" : 65,
				"z" : -4
			},
			"seller" : "K9us",
			"time" : "2019/02/12",
			"type" : "buy",
			"volume" : 2500,
			"world" : "world"
		},
		{
			"amount" : 1,
			"buyer" : "NorraLigan",
			"location" : 
			{
				"x" : -9,
				"y" : 68,
				"z" : 18
			},
			"seller" : "sharonclaws",
			"time" : "2019/02/16",
			"type" : "buy",
			"volume" : 2000,
			"world" : "world"
		},
		{
			"amount" : 1,
			"buyer" : "BelegStrongbow",
			"location" : 
			{
				"x" : -106,
				"y" : 65,
				"z" : -4
			},
			"seller" : "K9us",
			"time" : "2019/02/19",
			"type" : "buy",
			"volume" : 1700,
			"world" : "world"
		},
		{
			"amount" : 1,
			"buyer" : "AshGreninja2579",
			"location" : 
			{
				"x" : -9,
				"y" : 68,
				"z" : 18
			},
			"seller" : "sharonclaws",
			"time" : "2019/02/21",
			"type" : "buy",
			"volume" : 2000,
			"world" : "world"
		},
		{
			"amount" : 1,
			"buyer" : "Vivifoxx",
			"location" : 
			{
				"x" : -106,
				"y" : 65,
				"z" : -4
			},
			"seller" : "K9us",
			"time" : "2019/02/24",
			"type" : "buy",
			"volume" : 1700,
			"world" : "world"
		},
		{
			"amount" : 1,
			"buyer" : "lusacu420",
			"location" : 
			{
				"x" : -9,
				"y" : 68,
				"z" : 18
			},
			"seller" : "sharonclaws",
			"time" : "2019/03/08",
			"type" : "buy",
			"volume" : 2000,
			"world" : "world"
		},
		{
			"amount" : 1,
			"buyer" : "lusacu420",
			"location" : 
			{
				"x" : -9,
				"y" : 68,
				"z" : 18
			},
			"seller" : "sharonclaws",
			"time" : "2019/03/17",
			"type" : "buy",
			"volume" : 2000,
			"world" : "world"
		},
		{
			"amount" : 1,
			"buyer" : "Cesium_Knight",
			"location" : 
			{
				"x" : -9,
				"y" : 68,
				"z" : 18
			},
			"seller" : "sharonclaws",
			"time" : "2019/03/29",
			"type" : "buy",
			"volume" : 2000,
			"world" : "world"
		},
		{
			"amount" : 1,
			"buyer" : "Man_Chicken",
			"location" : 
			{
				"x" : -106,
				"y" : 65,
				"z" : -4
			},
			"seller" : "K9us",
			"time" : "2019/03/30",
			"type" : "buy",
			"volume" : 1700,
			"world" : "world"
		}
	]
}