{
	"item name" : "Diamond Pickaxe#3O",
	"transactions" : 
	[
		{
			"amount" : 1,
			"buyer" : "NullCase",
			"location" : 
			{
				"x" : -7,
				"y" : 71,
				"z" : 17
			},
			"seller" : "TheScrubJay",
			"time" : "2018/10/30",
			"volume" : 78000,
			"world" : "world"
		},
		{
			"amount" : 1,
			"buyer" : "daggvad",
			"location" : 
			{
				"x" : -7,
				"y" : 71,
				"z" : 17
			},
			"seller" : "TheScrubJay",
			"time" : "2018/10/30",
			"volume" : 78000,
			"world" : "world"
		},
		{
			"amount" : 1,
			"buyer" : "G4t1t4M1m0s4",
			"location" : 
			{
				"x" : -7,
				"y" : 71,
				"z" : 17
			},
			"seller" : "TheScrubJay",
			"time" : "2018/11/03",
			"volume" : 78000,
			"world" : "world"
		},
		{
			"amount" : 1,
			"buyer" : "dr_potato123",
			"location" : 
			{
				"x" : -7,
				"y" : 71,
				"z" : 17
			},
			"seller" : "TheScrubJay",
			"time" : "2018/11/25",
			"volume" : 73000,
			"world" : "world"
		},
		{
			"amount" : 1,
			"buyer" : "TheEzieDawg",
			"location" : 
			{
				"x" : 30,
				"y" : 83,
				"z" : -22
			},
			"seller" : "K9us",
			"time" : "2018/11/27",
			"volume" : 60000,
			"world" : "world"
		},
		{
			"amount" : 1,
			"buyer" : "dandenoth",
			"location" : 
			{
				"x" : -14,
				"y" : 65,
				"z" : 15
			},
			"seller" : "TheScrubJay",
			"time" : "2019/03/16",
			"volume" : 37000,
			"world" : "world"
		},
		{
			"amount" : 1,
			"buyer" : "dandenoth",
			"location" : 
			{
				"x" : -14,
				"y" : 65,
				"z" : 15
			},
			"seller" : "TheScrubJay",
			"time" : "2019/03/29",
			"volume" : 37000,
			"world" : "world"
		}
	]
}