{
	"item name" : "Enchanted Book#4f",
	"transactions" : 
	[
		{
			"amount" : 1,
			"buyer" : "AteUrC00ki35",
			"location" : 
			{
				"x" : -14,
				"y" : 64,
				"z" : 13
			},
			"seller" : "sharonclaws",
			"time" : "2018/11/01",
			"volume" : 12000,
			"world" : "world"
		},
		{
			"amount" : 1,
			"buyer" : "__Wildfire_",
			"location" : 
			{
				"x" : -13,
				"y" : 57,
				"z" : 7
			},
			"seller" : "sharonclaws",
			"time" : "2018/11/25",
			"volume" : 3000,
			"world" : "world"
		},
		{
			"amount" : 1,
			"buyer" : "freakdown",
			"location" : 
			{
				"x" : 37,
				"y" : 63,
				"z" : -51
			},
			"seller" : "K9us",
			"time" : "2018/11/28",
			"volume" : 2600,
			"world" : "world"
		},
		{
			"amount" : 1,
			"buyer" : "AspenGamgee",
			"location" : 
			{
				"x" : 32,
				"y" : 78,
				"z" : 12
			},
			"seller" : "__Wildfire_",
			"time" : "2019/03/06",
			"volume" : 2500,
			"world" : "world"
		}
	]
}