{
	"item name" : "Enchanted Book#Q",
	"transactions" : 
	[
		{
			"amount" : 2,
			"buyer" : "NullCase",
			"location" : 
			{
				"x" : 47,
				"y" : 73,
				"z" : -21
			},
			"seller" : "K9us",
			"time" : "2018/09/19",
			"type" : "buy",
			"volume" : 9000,
			"world" : "world"
		},
		{
			"amount" : 2,
			"buyer" : "sparkXstorm",
			"location" : 
			{
				"x" : 58,
				"y" : 51,
				"z" : -62
			},
			"seller" : "K9us",
			"time" : "2019/07/04",
			"type" : "buy",
			"volume" : 1120,
			"world" : "world"
		},
		{
			"amount" : 2,
			"buyer" : "Oaken_Ralph",
			"location" : 
			{
				"x" : 55,
				"y" : 88,
				"z" : 21
			},
			"seller" : "Remix_D_Miner",
			"time" : "2019/10/31",
			"type" : "buy",
			"volume" : 2000,
			"world" : "world"
		}
	]
}