{
	"item name" : "Iron Boots",
	"transactions" : 
	[
		{
			"amount" : 2,
			"buyer" : "Technerd05",
			"location" : 
			{
				"x" : -312,
				"y" : 72,
				"z" : -428
			},
			"seller" : "EnDristON",
			"time" : "2019/04/14",
			"volume" : 600,
			"world" : "world"
		},
		{
			"amount" : 2,
			"buyer" : "Shadows_Strike",
			"location" : 
			{
				"x" : 1409,
				"y" : 73,
				"z" : 2300
			},
			"seller" : "Spectate_Nate",
			"time" : "2020/03/29",
			"volume" : 0,
			"world" : "world"
		}
	]
}