{
	"item name" : "Iron Boots#1c",
	"transactions" : 
	[
		{
			"amount" : 1,
			"buyer" : "DjungelJarl",
			"location" : 
			{
				"x" : 30,
				"y" : 71,
				"z" : -19
			},
			"seller" : "K9us",
			"time" : "2018/09/14",
			"volume" : 39000,
			"world" : "world"
		},
		{
			"amount" : 1,
			"buyer" : "frozenhammerz",
			"location" : 
			{
				"x" : 32,
				"y" : 70,
				"z" : -19
			},
			"seller" : "K9us",
			"time" : "2018/10/10",
			"volume" : 4500,
			"world" : "world"
		},
		{
			"amount" : 1,
			"buyer" : "NorraLigan",
			"location" : 
			{
				"x" : 32,
				"y" : 70,
				"z" : -19
			},
			"seller" : "K9us",
			"time" : "2018/10/21",
			"volume" : 4500,
			"world" : "world"
		}
	]
}